Workbook
Name _Order1: 255
Name _Order2: 255
Name FWS: [1]参数表!$C$2:$C$6
Name XQ: [1]参数表!$B$2:$B$9
Name 厨卫规格: [2]参数!$F$2:$F$11
Name 单位用量: '[3]1-1 定额【5.0】'!$O:$O
Name 单位用量: '[4]1-1 定额【5.0】'!$O:$O
Name 辅材材料单价: '[3]1-1 定额【5.0】'!$S:$S
Name 辅材材料单价: '[4]1-1 定额【5.0】'!$S:$S
Name 辅材采购损耗率: '[3]1-1 定额【5.0】'!$P:$P
Name 辅材采购损耗率: '[4]1-1 定额【5.0】'!$P:$P
Name 辅材施工损耗率: '[3]1-1 定额【5.0】'!$R:$R
Name 辅材施工损耗率: '[4]1-1 定额【5.0】'!$R:$R
Name 辅材运输损耗率: '[3]1-1 定额【5.0】'!$Q:$Q
Name 辅材运输损耗率: '[4]1-1 定额【5.0】'!$Q:$Q
Name 户型: [2]参数!$G$2:$G$14
Name 水电套餐: [2]参数!$D$2:$D$4
Name 水电套餐品牌: [2]参数!$E$2:$E$6
Name 状态: [2]参数!$H$2:$H$8

Sheet 基装
B1: 工程预算清单 | K1: 项目编号：
A2: 序号 | B2: 项目名称 | C2: 单位 | D2: 物料编码 | E2: 主材损耗率 | F2: 主材单价 | G2: 施工单价 | H2: 工程量 | I2: 小计 | J2: 计算规则 | K2: 项目特征描述
A3: 一 | I3: =SUM(I4:I22) -> 0
A4: =+ROW()-ROW($A$3) -> 1 | B4: 墙体拆除（120墙） | C4: =VLOOKUP(B4,'报价表 最新'!A:B,2,0) -> 平米 | J4: =VLOOKUP(B4,'报价表 最新'!A:F,4,0) -> 按拆除面积计算，厚度超出部分按比例折算 | K4: =VLOOKUP(B4,'报价表 最新'!A:F,5,0) -> 拆除120墙体
A5: =+ROW()-ROW($A$3) -> 2 | B5: 墙体拆除（240墙） | C5: =VLOOKUP(B5,'报价表 最新'!A:B,2,0) -> 平米 | J5: =VLOOKUP(B5,'报价表 最新'!A:F,4,0) -> 按拆除面积计算，厚度超出部分按比例折算 | K5: =VLOOKUP(B5,'报价表 最新'!A:F,5,0) -> 拆除240墙体
A6: =+ROW()-ROW($A$3) -> 3 | B6: 拆除保温层 | C6: =VLOOKUP(B6,'报价表 最新'!A:B,2,0) -> 平米 | J6: =VLOOKUP(B6,'报价表 最新'!A:F,4,0) -> 按拆除面积计算 | K6: =VLOOKUP(B6,'报价表 最新'!A:F,5,0) -> 拆除保温层或外墙漆
A7: =+ROW()-ROW($A$3) -> 4 | B7: 拆除外墙砖 | C7: =VLOOKUP(B7,'报价表 最新'!A:B,2,0) -> 平米 | J7: =VLOOKUP(B7,'报价表 最新'!A:F,4,0) -> 按拆除面积计算 | K7: =VLOOKUP(B7,'报价表 最新'!A:F,5,0) -> 拆除外墙砖
A8: =+ROW()-ROW($A$3) -> 5 | B8: 拆除室外/室内混凝土楼梯 | C8: =VLOOKUP(B8,'报价表 最新'!A:B,2,0) -> 步 | J8: =VLOOKUP(B8,'报价表 最新'!A:F,4,0) -> 按踏步数计算 | K8: =VLOOKUP(B8,'报价表 最新'!A:F,5,0) -> 包含室外/室内楼梯拆除、现场清理
A9: =+ROW()-ROW($A$3) -> 6 | B9: 门窗、栏杆拆除 | C9: =VLOOKUP(B9,'报价表 最新'!A:B,2,0) -> 米 | J9: =VLOOKUP(B9,'报价表 最新'!A:F,4,0) -> 1.按拆除米数计算 2.最低收费2米 3.客户不要的工人自行处理，不予收费 | K9: =VLOOKUP(B9,'报价表 最新'!A:F,5,0) -> 拆除门、门套及门套基层，拆除防护栏杆
A10: =+ROW()-ROW($A$3) -> 7 | B10: 新建60墙（红砖） | C10: =VLOOKUP(B10,'报价表 最新'!A:B,2,0) -> 平米 | J10: =VLOOKUP(B10,'报价表 最新'!A:F,4,0) -> 按新建面积计算 | K10: =VLOOKUP(B10,'报价表 最新'!A:F,5,0) -> 包含铲墙皮、植筋、墙体砌筑、新旧墙体交接处挂网、墙面抹灰
A11: =+ROW()-ROW($A$3) -> 8 | B11: 新建120墙（红砖） | C11: 平米 | J11: =VLOOKUP(B11,'报价表 最新'!A:F,4,0) -> 按新建面积计算 主要用于厨卫、生活阳台及承重区域 | K11: =VLOOKUP(B11,'报价表 最新'!A:F,5,0) -> 包含铲墙皮、植筋、墙体砌筑、新旧墙体交接处挂网、墙面抹灰
A12: 9 | B12: 新建120弧形墙（红砖） | C12: 平米 | J12: =VLOOKUP(B12,'报价表 最新'!A:F,4,0) -> 按新建面积计算 主要用于厨卫、生活阳台及承重区域 | K12: =VLOOKUP(B12,'报价表 最新'!A:F,5,0) -> 包含铲墙皮、植筋、墙体砌筑、新旧墙体交接处挂网、墙面抹灰
A13: =+ROW()-ROW($A$3) -> 10 | B13: 新建240墙（红砖） | C13: =VLOOKUP(B13,'报价表 最新'!A:B,2,0) -> 平米 | J13: =VLOOKUP(B13,'报价表 最新'!A:F,4,0) -> 按新建面积计算 主要用于厨卫、生活阳台及承重区域 | K13: =VLOOKUP(B13,'报价表 最新'!A:F,5,0) -> 包含铲墙皮、植筋、墙体砌筑、新旧墙体交接处挂网、墙面抹灰
A14: =+ROW()-ROW($A$3) -> 11 | B14: 门窗洞修补（水泥砂浆） | C14: =VLOOKUP(B14,'报价表 最新'!A:B,2,0) -> 个 | J14: =VLOOKUP(B14,'报价表 最新'!A:F,4,0) -> 按个数计算 | K14: =VLOOKUP(B14,'报价表 最新'!A:F,5,0) -> 水泥砂浆抹灰修补，适用于打拆后的门窗洞修补，不含过梁
A15: =+ROW()-ROW($A$3) -> 12 | B15: 新建单边门垛（200mm宽以内） | C15: =VLOOKUP(B15,'报价表 最新'!A:B,2,0) -> 个 | J15: =VLOOKUP(B15,'报价表 最新'!A:F,4,0) -> 按个数计算 | K15: =VLOOKUP(B15,'报价表 最新'!A:F,5,0) -> 包含植筋、墙体砌筑、新旧墙体交接处挂网
A16: =+ROW()-ROW($A$3) -> 13 | B16: 新建壁龛 | C16: =VLOOKUP(B16,'报价表 最新'!A:B,2,0) -> 格 | J16: =VLOOKUP(B16,'报价表 最新'!A:F,4,0) -> 按个数计算 | K16: =VLOOKUP(B16,'报价表 最新'!A:F,5,0) -> 包含墙体砌筑、新旧墙体交接处挂网
A17: =+ROW()-ROW($A$3) -> 14 | B17: 门过梁施工（1.2米） | C17: =VLOOKUP(B17,'报价表 最新'!A:B,2,0) -> 根 | J17: =VLOOKUP(B17,'报价表 最新'!A:F,4,0) -> 按根数计算，墙厚140mm以内的墙使用1根，墙厚>140mm的墙使用2根 | K17: =VLOOKUP(B17,'报价表 最新'!A:F,5,0) -> 门洞宽900mm以内
A18: =+ROW()-ROW($A$3) -> 15 | B18: 门过梁施工（2米） | C18: =VLOOKUP(B18,'报价表 最新'!A:B,2,0) -> 根 | J18: =VLOOKUP(B18,'报价表 最新'!A:F,4,0) -> 按根数计算，墙厚140mm以内的墙使用1根，墙厚>140mm的墙使用2根 | K18: =VLOOKUP(B18,'报价表 最新'!A:F,5,0) -> 门洞宽1600mm以内
A19: =+ROW()-ROW($A$3) -> 16 | B19: 门钢架过梁施工（3米） | C19: =VLOOKUP(B19,'报价表 最新'!A:B,2,0) -> 根 | J19: =VLOOKUP(B19,'报价表 最新'!A:F,4,0) -> 按根数计算，墙厚140mm以内的墙使用1根，墙厚>140mm的墙使用2根 | K19: =VLOOKUP(B19,'报价表 最新'!A:F,5,0) -> 门洞宽度大于2米小于2.6米的
A20: =+ROW()-ROW($A$3) -> 17 | B20: 门套木基层 | C20: =VLOOKUP(B20,'报价表 最新'!A:B,2,0) -> 米 | J20: =VLOOKUP(B20,'报价表 最新'!A:F,4,0) -> 按延长米计算 | K20: =VLOOKUP(B20,'报价表 最新'!A:F,5,0) -> 门套基层制作及安装
A21: =+ROW()-ROW($A$3) -> 18 | B21: 双排钢架隔墙（暗藏式门基层含双面封板） | C21: =VLOOKUP(B21,'报价表 最新'!A:B,2,0) -> 平米 | J21: =VLOOKUP(B21,'报价表 最新'!A:F,4,0) -> 按施工面积计算 | K21: =VLOOKUP(B21,'报价表 最新'!A:F,5,0) -> 双排钢架隔墙及双面封基层板施工
A22: =+ROW()-ROW($A$3) -> 19 | B22: 空鼓拆除及修复 | C22: =VLOOKUP(B22,'报价表 最新'!A:B,2,0) -> 平米 | J22: =VLOOKUP(B22,'报价表 最新'!A:F,4,0) -> 单处空鼓面积小于1㎡按1㎡计算，大于1㎡按实际面积计算 | K22: =VLOOKUP(B22,'报价表 最新'!A:F,5,0) -> 空鼓拆除及修复处理等
A23: 二
A24: 1 | B24: 别墅水电全改（进口PPR） | C24: =VLOOKUP(B24,'报价表 最新'!A:B,2,0) -> 平米 | J24: =VLOOKUP(B24,'报价表 最新'!A:F,4,0) -> 按合同面积计算，超出标准部分，费用计算规则详见《水电计价标准》 | K24: =VLOOKUP(B24,'报价表 最新'!A:F,5,0) -> 包含开槽、开孔、强弱电改造、空开关调试、给排水改造、通水通电测试等
A25: 三
A26: =+ROW()-ROW(A25) -> 1 | B26: 陶粒回填+保护层 | C26: =VLOOKUP(B26,'报价表 最新'!A:B,2,0) -> 立方 | J26: =VLOOKUP(B26,'报价表 最新'!A:F,4,0) -> 按回填方量计算 | K26: =VLOOKUP(B26,'报价表 最新'!A:F,5,0) -> 陶粒回填找平
A27: =+ROW()-ROW(A25) -> 2 | B27: 水泥砂浆精找平 | C27: =VLOOKUP(B27,'报价表 最新'!A:B,2,0) -> 平米 | J27: =VLOOKUP(B27,'报价表 最新'!A:F,4,0) -> 按施工面积计算 找平厚度30mm以内，超出部分每增加10mm厚增加15元/平米 | K27: =VLOOKUP(B27,'报价表 最新'!A:F,5,0) -> 水泥砂浆找平，找平厚度≤30mm
A28: =+ROW()-ROW(A25) -> 3 | B28: 实木地板安装 | C28: =VLOOKUP(B28,'报价表 最新'!A:B,2,0) -> 平米 | E28: 0.05 | J28: =VLOOKUP(B28,'报价表 最新'!A:F,4,0) -> 按施工面积计算 | K28: =VLOOKUP(B28,'报价表 最新'!A:F,5,0) -> 含安装地垫、木地板、配件安装，完工保护等
A29: =+ROW()-ROW(A25) -> 4 | B29: 踢脚线安装 | C29: =VLOOKUP(B29,'报价表 最新'!A:B,2,0) -> 米 | E29: 0.07 | J29: =VLOOKUP(B29,'报价表 最新'!A:F,4,0) -> 按延长米计算 | K29: =VLOOKUP(B29,'报价表 最新'!A:F,5,0) -> 含安装踢脚线、打胶等
A30: =+ROW()-ROW(A25) -> 5 | B30: 地板收口条 | C30: 根 | J30: 按根数计算
A31: =+ROW()-ROW(A25) -> 6 | B31: 墙面石膏腻子顺平处理(干区) | C31: =VLOOKUP(B31,'报价表 最新'!A:B,2,0) -> 平米 | J31: =VLOOKUP(B31,'报价表 最新'!A:F,4,0) -> 按施工面积计算，门窗面积按50%计算 | K31: =VLOOKUP(B31,'报价表 最新'!A:F,5,0) -> 刷界面剂、挂网、补钉眼、铲胶、贴纸胶带、石膏找平、阴阳角处理、两遍腻子施工、打磨和一遍底漆施工等
A32: =+ROW()-ROW(A25) -> 7 | B32: 乳胶漆喷涂 | C32: =VLOOKUP(B32,'报价表 最新'!A:B,2,0) -> 平米 | D32: 纯净520A+竹炭抗菌五合一（喷涂） | J32: =VLOOKUP(B32,'报价表 最新'!A:F,4,0) -> 按施工面积计算 分色费另计 | K32: =VLOOKUP(B32,'报价表 最新'!A:F,5,0) -> 面漆喷涂施工
A33: =+ROW()-ROW(A25) -> 8 | B33: 窗台石安装 | C33: =VLOOKUP(B33,'报价表 最新'!A:B,2,0) -> 米 | J33: =VLOOKUP(B33,'报价表 最新'!A:F,4,0) -> 按延长米计算 | K33: =VLOOKUP(B33,'报价表 最新'!A:F,5,0) -> 成品安装
A34: =+ROW()-ROW(A25) -> 9 | B34: 轻钢龙骨单层石膏板吊顶（边顶） | C34: =VLOOKUP(B34,'报价表 最新'!A:B,2,0) -> 平米 | J34: =VLOOKUP(B34,'报价表 最新'!A:F,4,0) -> 按展开面积计算 | K34: =VLOOKUP(B34,'报价表 最新'!A:F,5,0) -> 包含打眼、吊筋、主副龙骨、单层石膏板安装、转角加固等
A35: =+ROW()-ROW(A25) -> 10 | B35: 吊顶眉线 | C35: =VLOOKUP(B35,'报价表 最新'!A:B,2,0) -> 米 | J35: =VLOOKUP(B35,'报价表 最新'!A:F,4,0) -> 按延长米计算 （宽度20mm以内，高度200mm以内，超出费用另计。高度每增加100mm增加15元/米） | K35: =VLOOKUP(B35,'报价表 最新'!A:F,5,0) -> 包含吊顶一圈、边顶或灯槽反边的眉线制作安装双层石膏板制作及安装（吊顶单算，这个只是眉线）
A36: =+ROW()-ROW(A25) -> 11 | B36: 窗帘盒 | C36: =VLOOKUP(B36,'报价表 最新'!A:B,2,0) -> 米 | J36: =VLOOKUP(B36,'报价表 最新'!A:F,4,0) -> 按延长米计算 | K36: =VLOOKUP(B36,'报价表 最新'!A:F,5,0) -> 包含窗帘盒制作安装、基层加固等
A37: =+ROW()-ROW(A25) -> 12 | B37: 开设备孔（空调/浴霸/暖风机） | C37: =VLOOKUP(B37,'报价表 最新'!A:B,2,0) -> 米 | J37: =VLOOKUP(B37,'报价表 最新'!A:F,4,0) -> 按米数计算，单个设备孔最低收费1米 | K37: =VLOOKUP(B37,'报价表 最新'!A:F,5,0) -> 包含放线、定位、开孔及加固处理等
A38: =+ROW()-ROW(A25) -> 13 | B38: 顶面石膏腻子顺平处理（干区） | C38: =VLOOKUP(B38,'报价表 最新'!A:B,2,0) -> 平米 | J38: =VLOOKUP(B38,'报价表 最新'!A:F,4,0) -> 按施工面积计算，门窗面积按50%计算 | K38: =VLOOKUP(B38,'报价表 最新'!A:F,5,0) -> 刷界面剂、挂网、补钉眼、铲胶、贴纸胶带、石膏找平、阴阳角处理、两遍腻子施工、打磨和一遍底漆施工等
A39: =+ROW()-ROW(A25) -> 14 | B39: 乳胶漆喷涂 | C39: =VLOOKUP(B39,'报价表 最新'!A:B,2,0) -> 平米 | D39: 纯净520防霉防潮三合一环保内墙漆 | J39: =VLOOKUP(B39,'报价表 最新'!A:F,4,0) -> 按施工面积计算 分色费另计 | K39: =VLOOKUP(B39,'报价表 最新'!A:F,5,0) -> 面漆喷涂施工
A40: =+ROW()-ROW(A25) -> 15 | B40: 平开门（含门套、门、五金） | C40: =VLOOKUP(B40,'报价表 最新'!A:B,2,0) -> 套 | D40: M2平开门 | J40: =VLOOKUP(B40,'报价表 最新'!A:F,4,0) -> 按套数计算 | K40: =VLOOKUP(B40,'报价表 最新'!A:F,5,0) -> 成品安装(含门套、门、五金)
A41: 四
A42: =+ROW()-ROW(A41) -> 1 | B42: 水泥砂浆精找平 | C42: =VLOOKUP(B42,'报价表 最新'!A:B,2,0) -> 平米 | J42: =VLOOKUP(B42,'报价表 最新'!A:F,4,0) -> 按施工面积计算 找平厚度30mm以内，超出部分每增加10mm厚增加15元/平米 | K42: =VLOOKUP(B42,'报价表 最新'!A:F,5,0) -> 水泥砂浆找平，找平厚度≤30mm
A43: =+ROW()-ROW(A41) -> 2 | B43: 实木地板安装 | C43: =VLOOKUP(B43,'报价表 最新'!A:B,2,0) -> 平米 | E43: 0.05 | J43: =VLOOKUP(B43,'报价表 最新'!A:F,4,0) -> 按施工面积计算 | K43: =VLOOKUP(B43,'报价表 最新'!A:F,5,0) -> 含安装地垫、木地板、配件安装，完工保护等
A44: =+ROW()-ROW(A41) -> 3 | B44: 踢脚线安装 | C44: =VLOOKUP(B44,'报价表 最新'!A:B,2,0) -> 米 | E44: 0.07 | J44: =VLOOKUP(B44,'报价表 最新'!A:F,4,0) -> 按延长米计算 | K44: =VLOOKUP(B44,'报价表 最新'!A:F,5,0) -> 含安装踢脚线、打胶等
A45: =+ROW()-ROW(A41) -> 4 | B45: 收口条 | C45: 根 | J45: 按根数计算
A46: =+ROW()-ROW(A41) -> 5 | B46: 门槛石安装 | C46: =VLOOKUP(B46,'报价表 最新'!A:B,2,0) -> 米 | J46: =VLOOKUP(B46,'报价表 最新'!A:F,4,0) -> 按延长米计算，不足一米按一米计算 | K46: =VLOOKUP(B46,'报价表 最新'!A:F,5,0) -> 成品安装
A47: =+ROW()-ROW(A41) -> 6 | B47: 窗台石安装 | C47: =VLOOKUP(B47,'报价表 最新'!A:B,2,0) -> 米 | J47: =VLOOKUP(B47,'报价表 最新'!A:F,4,0) -> 按延长米计算 | K47: =VLOOKUP(B47,'报价表 最新'!A:F,5,0) -> 成品安装
A48: =+ROW()-ROW(A41) -> 7 | B48: 墙面石膏腻子顺平处理(干区) | C48: =VLOOKUP(B48,'报价表 最新'!A:B,2,0) -> 平米 | J48: =VLOOKUP(B48,'报价表 最新'!A:F,4,0) -> 按施工面积计算，门窗面积按50%计算 | K48: =VLOOKUP(B48,'报价表 最新'!A:F,5,0) -> 刷界面剂、挂网、补钉眼、铲胶、贴纸胶带、石膏找平、阴阳角处理、两遍腻子施工、打磨和一遍底漆施工等
A49: =+ROW()-ROW(A41) -> 8 | B49: 乳胶漆喷涂 | C49: =VLOOKUP(B49,'报价表 最新'!A:B,2,0) -> 平米 | D49: 丝绸艺术漆：010601-0003 | J49: =VLOOKUP(B49,'报价表 最新'!A:F,4,0) -> 按施工面积计算 分色费另计 | K49: =VLOOKUP(B49,'报价表 最新'!A:F,5,0) -> 面漆喷涂施工
A50: =+ROW()-ROW(A41) -> 9 | B50: 轻钢龙骨单层石膏板吊顶（边顶） | C50: =VLOOKUP(B50,'报价表 最新'!A:B,2,0) -> 平米 | J50: =VLOOKUP(B50,'报价表 最新'!A:F,4,0) -> 按展开面积计算 | K50: =VLOOKUP(B50,'报价表 最新'!A:F,5,0) -> 包含打眼、吊筋、主副龙骨、单层石膏板安装、转角加固等
A51: =+ROW()-ROW(#REF!) -> #REF! | B51: 轻钢龙骨单层石膏板吊顶（平顶） | C51: =VLOOKUP(B51,'报价表 最新'!A:B,2,0) -> 平米 | J51: =VLOOKUP(B51,'报价表 最新'!A:F,4,0) -> 按展开面积计算 | K51: =VLOOKUP(B51,'报价表 最新'!A:F,5,0) -> 包含打眼、吊筋、主副龙骨、单层石膏板安装、转角加固等
A52: =+ROW()-ROW(A41) -> 11 | B52: 吊顶眉线 | C52: =VLOOKUP(B52,'报价表 最新'!A:B,2,0) -> 米 | J52: =VLOOKUP(B52,'报价表 最新'!A:F,4,0) -> 按延长米计算 （宽度20mm以内，高度200mm以内，超出费用另计。高度每增加100mm增加15元/米） | K52: =VLOOKUP(B52,'报价表 最新'!A:F,5,0) -> 包含吊顶一圈、边顶或灯槽反边的眉线制作安装双层石膏板制作及安装（吊顶单算，这个只是眉线）
A53: =+ROW()-ROW(A41) -> 12 | B53: 窗帘盒 | C53: =VLOOKUP(B53,'报价表 最新'!A:B,2,0) -> 米 | J53: =VLOOKUP(B53,'报价表 最新'!A:F,4,0) -> 按延长米计算 | K53: =VLOOKUP(B53,'报价表 最新'!A:F,5,0) -> 包含窗帘盒制作安装、基层加固等
A54: =+ROW()-ROW(A41) -> 13 | B54: 开设备孔（空调/浴霸/暖风机） | C54: =VLOOKUP(B54,'报价表 最新'!A:B,2,0) -> 米 | J54: =VLOOKUP(B54,'报价表 最新'!A:F,4,0) -> 按米数计算，单个设备孔最低收费1米 | K54: =VLOOKUP(B54,'报价表 最新'!A:F,5,0) -> 包含放线、定位、开孔及加固处理等
A55: =+ROW()-ROW(A41) -> 14 | B55: 顶面石膏腻子顺平处理（干区） | C55: =VLOOKUP(B55,'报价表 最新'!A:B,2,0) -> 平米 | J55: =VLOOKUP(B55,'报价表 最新'!A:F,4,0) -> 按施工面积计算，门窗面积按50%计算 | K55: =VLOOKUP(B55,'报价表 最新'!A:F,5,0) -> 刷界面剂、挂网、补钉眼、铲胶、贴纸胶带、石膏找平、阴阳角处理、两遍腻子施工、打磨和一遍底漆施工等
A56: =+ROW()-ROW(A41) -> 15 | B56: 乳胶漆喷涂 | C56: =VLOOKUP(B56,'报价表 最新'!A:B,2,0) -> 平米 | D56: 纯净520防霉防潮三合一环保内墙漆 | J56: =VLOOKUP(B56,'报价表 最新'!A:F,4,0) -> 按施工面积计算 分色费另计 | K56: =VLOOKUP(B56,'报价表 最新'!A:F,5,0) -> 面漆喷涂施工
A57: =+ROW()-ROW(A41) -> 16 | B57: 隔断玻璃移门（主卧门厅） | C57: 平米 | J57: 按展开面积计算
A58: =+ROW()-ROW(A41) -> 17 | B58: 隔断玻璃移门（书房） | C58: 米 | J58: 按展开面积计算
A59: =+ROW()-ROW(A41) -> 18 | B59: CLEAF饰面-隐藏移门，不带锁 | C59: 樘 | J59: 按门数计算
A60: 五
A61: =+ROW()-ROW(A60) -> 1 | B61: 陶粒回填+保护层 | C61: =VLOOKUP(B61,'报价表 最新'!A:B,2,0) -> 立方 | J61: =VLOOKUP(B61,'报价表 最新'!A:F,4,0) -> 按回填方量计算 | K61: =VLOOKUP(B61,'报价表 最新'!A:F,5,0) -> 陶粒回填找平
A62: =+ROW()-ROW(A60) -> 2 | B62: 水泥砂浆精找平 | C62: =VLOOKUP(B62,'报价表 最新'!A:B,2,0) -> 平米 | J62: =VLOOKUP(B62,'报价表 最新'!A:F,4,0) -> 按施工面积计算 找平厚度30mm以内，超出部分每增加10mm厚增加15元/平米 | K62: =VLOOKUP(B62,'报价表 最新'!A:F,5,0) -> 水泥砂浆找平，找平厚度≤30mm
A63: =+ROW()-ROW(A60) -> 3 | B63: 实木地板安装 | C63: =VLOOKUP(B63,'报价表 最新'!A:B,2,0) -> 平米 | E63: 0.05 | J63: =VLOOKUP(B63,'报价表 最新'!A:F,4,0) -> 按施工面积计算 | K63: =VLOOKUP(B63,'报价表 最新'!A:F,5,0) -> 含安装地垫、木地板、配件安装，完工保护等
A64: =+ROW()-ROW(A60) -> 4 | B64: 踢脚线安装 | C64: =VLOOKUP(B64,'报价表 最新'!A:B,2,0) -> 米 | E64: 0.07 | J64: =VLOOKUP(B64,'报价表 最新'!A:F,4,0) -> 按延长米计算 | K64: =VLOOKUP(B64,'报价表 最新'!A:F,5,0) -> 含安装踢脚线、打胶等
A65: =+ROW()-ROW(A60) -> 5 | B65: 收口条 | C65: 根 | J65: 按根数计算
A66: =+ROW()-ROW(A60) -> 6 | B66: 窗台石安装 | C66: =VLOOKUP(B66,'报价表 最新'!A:B,2,0) -> 米 | J66: =VLOOKUP(B66,'报价表 最新'!A:F,4,0) -> 按延长米计算 | K66: =VLOOKUP(B66,'报价表 最新'!A:F,5,0) -> 成品安装
A67: =+ROW()-ROW(A60) -> 7 | B67: 墙面石膏腻子顺平处理(干区) | C67: =VLOOKUP(B67,'报价表 最新'!A:B,2,0) -> 平米 | J67: =VLOOKUP(B67,'报价表 最新'!A:F,4,0) -> 按施工面积计算，门窗面积按50%计算 | K67: =VLOOKUP(B67,'报价表 最新'!A:F,5,0) -> 刷界面剂、挂网、补钉眼、铲胶、贴纸胶带、石膏找平、阴阳角处理、两遍腻子施工、打磨和一遍底漆施工等
A68: =+ROW()-ROW(A60) -> 8 | B68: 乳胶漆喷涂 | C68: =VLOOKUP(B68,'报价表 最新'!A:B,2,0) -> 平米 | D68: 纯净520A+竹炭抗菌五合一（喷涂） | J68: =VLOOKUP(B68,'报价表 最新'!A:F,4,0) -> 按施工面积计算 分色费另计 | K68: =VLOOKUP(B68,'报价表 最新'!A:F,5,0) -> 面漆喷涂施工
A69: =+ROW()-ROW(A60) -> 9 | B69: 轻钢龙骨单层石膏板吊顶（边顶） | C69: =VLOOKUP(B69,'报价表 最新'!A:B,2,0) -> 平米 | J69: =VLOOKUP(B69,'报价表 最新'!A:F,4,0) -> 按展开面积计算 | K69: =VLOOKUP(B69,'报价表 最新'!A:F,5,0) -> 包含打眼、吊筋、主副龙骨、单层石膏板安装、转角加固等
A70: =+ROW()-ROW(A60) -> 10 | B70: 吊顶眉线 | C70: =VLOOKUP(B70,'报价表 最新'!A:B,2,0) -> 米 | J70: =VLOOKUP(B70,'报价表 最新'!A:F,4,0) -> 按延长米计算 （宽度20mm以内，高度200mm以内，超出费用另计。高度每增加100mm增加15元/米） | K70: =VLOOKUP(B70,'报价表 最新'!A:F,5,0) -> 包含吊顶一圈、边顶或灯槽反边的眉线制作安装双层石膏板制作及安装（吊顶单算，这个只是眉线）
A71: =+ROW()-ROW(A60) -> 11 | B71: 窗帘盒 | C71: =VLOOKUP(B71,'报价表 最新'!A:B,2,0) -> 米 | J71: =VLOOKUP(B71,'报价表 最新'!A:F,4,0) -> 按延长米计算 | K71: =VLOOKUP(B71,'报价表 最新'!A:F,5,0) -> 包含窗帘盒制作安装、基层加固等
A72: =+ROW()-ROW(A60) -> 12 | B72: 开设备孔（空调/浴霸/暖风机） | C72: =VLOOKUP(B72,'报价表 最新'!A:B,2,0) -> 米 | J72: =VLOOKUP(B72,'报价表 最新'!A:F,4,0) -> 按米数计算，单个设备孔最低收费1米 | K72: =VLOOKUP(B72,'报价表 最新'!A:F,5,0) -> 包含放线、定位、开孔及加固处理等
A73: =+ROW()-ROW(A60) -> 13 | B73: 顶面石膏腻子顺平处理（干区） | C73: =VLOOKUP(B73,'报价表 最新'!A:B,2,0) -> 平米 | J73: =VLOOKUP(B73,'报价表 最新'!A:F,4,0) -> 按施工面积计算，门窗面积按50%计算 | K73: =VLOOKUP(B73,'报价表 最新'!A:F,5,0) -> 刷界面剂、挂网、补钉眼、铲胶、贴纸胶带、石膏找平、阴阳角处理、两遍腻子施工、打磨和一遍底漆施工等
A74: =+ROW()-ROW(A60) -> 14 | B74: 乳胶漆喷涂 | C74: =VLOOKUP(B74,'报价表 最新'!A:B,2,0) -> 平米 | D74: 纯净520防霉防潮三合一环保内墙漆 | J74: =VLOOKUP(B74,'报价表 最新'!A:F,4,0) -> 按施工面积计算 分色费另计 | K74: =VLOOKUP(B74,'报价表 最新'!A:F,5,0) -> 面漆喷涂施工
A75: =+ROW()-ROW(A60) -> 15 | B75: 平开门（含门套、门、五金） | C75: =VLOOKUP(B75,'报价表 最新'!A:B,2,0) -> 套 | D75: M2平开门 | J75: =VLOOKUP(B75,'报价表 最新'!A:F,4,0) -> 按套数计算 | K75: =VLOOKUP(B75,'报价表 最新'!A:F,5,0) -> 成品安装(含门套、门、五金)
A76: 六
A77: =+ROW()-ROW($A$76) -> 1 | B77: 陶粒回填+保护层 | C77: =VLOOKUP(B77,'报价表 最新'!A:B,2,0) -> 立方 | J77: =VLOOKUP(B77,'报价表 最新'!A:F,4,0) -> 按回填方量计算 | K77: =VLOOKUP(B77,'报价表 最新'!A:F,5,0) -> 陶粒回填找平
A78: =+ROW()-ROW($A$76) -> 2 | B78: 门槛石安装 | C78: =VLOOKUP(B78,'报价表 最新'!A:B,2,0) -> 米 | J78: =VLOOKUP(B78,'报价表 最新'!A:F,4,0) -> 按延长米计算，不足一米按一米计算 | K78: =VLOOKUP(B78,'报价表 最新'!A:F,5,0) -> 成品安装
A79: =+ROW()-ROW($A$76) -> 3 | B79: 防水 | C79: =VLOOKUP(B79,'报价表 最新'!A:B,2,0) -> 平米 | J79: =VLOOKUP(B79,'报价表 最新'!A:F,4,0) -> 按施工面积计算 | K79: =VLOOKUP(B79,'报价表 最新'!A:F,5,0) -> 1.卫生间：沉箱地面清理，四周做R角处理，做柔性防水，防水超出沉箱上返300mm高，地面回填找平后做柔性防水+丙纶防水，墙面通用防水 2.厨房、阳台：地面清理后做柔性防水，墙面通用防水
A80: =+ROW()-ROW($A$76) -> 4 | B80: 防水保护层 | C80: =VLOOKUP(B80,'报价表 最新'!A:B,2,0) -> 平米 | J80: =VLOOKUP(B80,'报价表 最新'!A:F,4,0) -> 按施工面积计算 | K80: =VLOOKUP(B80,'报价表 最新'!A:F,5,0) -> 水泥河沙保护层施工
A81: =+ROW()-ROW($A$76) -> 5 | B81: 水泥河沙贴地砖（单边≤800mm） | C81: =VLOOKUP(B81,'报价表 最新'!A:B,2,0) -> 平米 | E81: 0.07 | J81: =VLOOKUP(B81,'报价表 最新'!A:F,4,0) -> 按施工面积计算 | K81: =VLOOKUP(B81,'报价表 最新'!A:F,5,0) -> 水泥砂浆贴砖，含墙砖背胶处理、瓷砖加工、缝隙清理、瓷砖面清理、勾缝、阳角保护等
A82: =+ROW()-ROW($A$76) -> 6 | B82: 瓷砖填缝升级美缝（卓高） | C82: =VLOOKUP(B82,'报价表 最新'!A:B,2,0) -> 平米 | J82: =VLOOKUP(B82,'报价表 最新'!A:F,4,0) -> 按施工面积计算 | K82: =VLOOKUP(B82,'报价表 最新'!A:F,5,0) -> 包含清理缝隙、美缝剂、人工施工等
A83: =+ROW()-ROW($A$76) -> 7 | B83: 水泥河沙贴墙砖（单边≤800mm） | C83: =VLOOKUP(B83,'报价表 最新'!A:B,2,0) -> 平米 | E83: 0.07 | J83: =VLOOKUP(B83,'报价表 最新'!A:F,4,0) -> 按施工面积计算 | K83: =VLOOKUP(B83,'报价表 最新'!A:F,5,0) -> 水泥砂浆贴砖，含墙砖背胶处理、瓷砖加工、缝隙清理、瓷砖面清理、勾缝、阳角保护等
A84: =+ROW()-ROW($A$76) -> 8 | B84: 瓷砖填缝升级美缝（卓高） | C84: =VLOOKUP(B84,'报价表 最新'!A:B,2,0) -> 平米 | J84: =VLOOKUP(B84,'报价表 最新'!A:F,4,0) -> 按施工面积计算 | K84: =VLOOKUP(B84,'报价表 最新'!A:F,5,0) -> 包含清理缝隙、美缝剂、人工施工等
A85: =+ROW()-ROW($A$76) -> 9 | B85: 轻钢龙骨单层防潮石膏板吊顶（平顶） | C85: =VLOOKUP(B85,'报价表 最新'!A:B,2,0) -> 平米 | J85: =VLOOKUP(B85,'报价表 最新'!A:F,4,0) -> 按展开面积计算 | K85: =VLOOKUP(B85,'报价表 最新'!A:F,5,0) -> 包含打眼、吊筋、主副龙骨、单层石膏板安装、转角加固等
A86: =+ROW()-ROW($A$76) -> 10 | B86: 开设备孔（空调/浴霸/暖风机） | C86: =VLOOKUP(B86,'报价表 最新'!A:B,2,0) -> 米 | J86: =VLOOKUP(B86,'报价表 最新'!A:F,4,0) -> 按米数计算，单个设备孔最低收费1米 | K86: =VLOOKUP(B86,'报价表 最新'!A:F,5,0) -> 包含放线、定位、开孔及加固处理等
A87: =+ROW()-ROW($A$76) -> 11 | B87: 检修口 | C87: =VLOOKUP(B87,'报价表 最新'!A:B,2,0) -> 个 | J87: =VLOOKUP(B87,'报价表 最新'!A:F,4,0) -> 按个数计算 | K87: =VLOOKUP(B87,'报价表 最新'!A:F,5,0) -> 包含放线、定位、开孔及加固处理等
A88: =+ROW()-ROW($A$76) -> 12 | B88: 顶面石膏腻子顺平处理（湿区） | C88: =VLOOKUP(B88,'报价表 最新'!A:B,2,0) -> 平米 | J88: =VLOOKUP(B88,'报价表 最新'!A:F,4,0) -> 按施工面积计算，门窗面积按50%计算 | K88: =VLOOKUP(B88,'报价表 最新'!A:F,5,0) -> 刷界面剂、挂网、补钉眼、铲胶、贴纸胶带、石膏找平、阴阳角处理、两遍腻子施工、打磨和一遍底漆施工等
A89: =+ROW()-ROW($A$76) -> 13 | B89: 乳胶漆喷涂 | C89: =VLOOKUP(B89,'报价表 最新'!A:B,2,0) -> 平米 | D89: 纯净520防霉防潮三合一环保内墙漆 | J89: =VLOOKUP(B89,'报价表 最新'!A:F,4,0) -> 按施工面积计算 分色费另计 | K89: =VLOOKUP(B89,'报价表 最新'!A:F,5,0) -> 面漆喷涂施工
A90: =+ROW()-ROW($A$76) -> 14 | B90: 淋浴房 | C90: 平米 | J90: 按展开面积计算
A91: =+ROW()-ROW($A$76) -> 15 | B91: 卫浴柜 | C91: 项
A92: =+ROW()-ROW($A$76) -> 16 | B92: 马桶 | C92: 套 | D92: 怡和 | J92: 按套数计算 | K92: 成品安装
A93: =+ROW()-ROW($A$76) -> 17 | B93: 花洒安装 | C93: =VLOOKUP(B93,'报价表 最新'!A:B,2,0) -> 套 | D93: 科勒 | J93: =VLOOKUP(B93,'报价表 最新'!A:F,4,0) -> 按套数计算 | K93: =VLOOKUP(B93,'报价表 最新'!A:F,5,0) -> 成品安装
A94: =+ROW()-ROW($A$76) -> 18 | B94: 面盆 | C94: 套 | D94: 科勒 | J94: 按套数计算 | K94: 成品安装
A95: =+ROW()-ROW($A$76) -> 19 | B95: 面盆龙头 | C95: 套 | D95: 科勒 | J95: 按套数计算 | K95: 成品安装
A96: =+ROW()-ROW($A$76) -> 20 | B96: 卫浴镜 | C96: 套 | J96: 按套数计算 | K96: 成品安装
A97: =+ROW()-ROW($A$76) -> 21 | B97: 地漏 | C97: 个
A98: =+ROW()-ROW($A$76) -> 22 | B98: 风暖安装 | C98: 个 | J98: 按套数计算 | K98: 成品安装
A99: =+ROW()-ROW($A$76) -> 23 | B99: 收口条 | C99: 根 | J99: 按根数计算
A100: =+ROW()-ROW($A$76) -> 24 | B100: 平开门（含门套、门、五金） | C100: =VLOOKUP(B100,'报价表 最新'!A:B,2,0) -> 套 | J100: =VLOOKUP(B100,'报价表 最新'!A:F,4,0) -> 按套数计算 | K100: =VLOOKUP(B100,'报价表 最新'!A:F,5,0) -> 成品安装(含门套、门、五金)
...

Sheet 报价表 最新
A2: 施工内容 | B2: 单位 | C2: 售价 | G2: 定额组编码
C3: 售价 | D3: 计算规则 | E3: 项目特征描述 | F3: 工艺标准
A4: 成品保护+安全防护 | B4: 平米 | C4: 15 | D4: 按合同面积计算 | E4: 成品保护包含入场检查，电梯厅、走廊、过道、门窗、气表、水表、烟感、可视电话等的保护，包含挂安全网及其他辅材综合考虑 | F4: 1.成品保护工艺：清扫墙地面→喜鹊字样胶带固定保护膜（电梯间膜、门窗保护膜、燃气表保护罩）→强弱电箱保护→施工自检； 合格标准：电梯、电梯厅、走廊、门窗、天然气表、强弱电箱等粘贴保护，要求平整方正，方向正确，且无翘脚； 2.安全防护工艺：关闭水电总闸→更换水龙头→接临时电箱→接临时照明→挂阳台安全网防护→施工自检； 合格标准：临时水电做好防漏防渗保护，安全网无漏洞或破损，安全网固定在安全挂钩上，无漏挂，安全网牢固无松动现象。 | G4: =#REF! -> #REF!
A5: 包管道隔音棉 | B5: 根 | C5: 50 | D5: 按根数计算 | E5: 排水管包隔音棉、扎带 | F5: 1.包管工艺：主给排水管道（含天花顶部的存水弯）隔音棉包裹→施工自检。 | G5: =#REF! -> #REF!
A6: 安全防护 | B6: 平米 | C6: 5 | D6: 按合同面积计算 | E6: 1.安全网种类、规格：安全网 2.其他辅材综合考虑 | F6: 1.安全防护工艺：关闭水电总闸→更换水龙头→接临时电箱→接临时照明→挂阳台安全网防护→施工自检； 2.合格标准：临时水电做好防漏防渗保护，安全网无漏洞或破损，安全网固定在安全挂钩上，无漏挂，安全网牢固无松动现象。 | G6: =#REF! -> #REF!
A7: 硬保护 | B7: 平米 | C7: 40 | D7: 按施工面积计算，最低收费400元 | E7: 施工区域及施工涉及到的活动区域地面3mm中纤板保护，地板区域的地面需做硬保护 | F7: 按物业或客户要求进行现场保护 | G7: =#REF! -> #REF!
A8: 铲墙皮 | B8: 平米 | C8: 18 | D8: 按合同面积计算 | E8: 包含原墙面顶面乳胶漆及基层的铲除、清理建渣等 | F8: 1.铲墙皮工艺：断水断电→接通临水临电→喷水枪湿润墙面反复3次→铲刀铲除白灰→施工自检；（不含保温层、外墙砖等的拆除） 2.合格标准：白灰剔除干净，能看见水泥基层，墙面剔除达率到95%以上。 | G8: =#REF! -> #REF!
A9: 涂刷墙地固 | B9: 平米 | C9: 8 | D9: 按合同面积计算 | E9: 滚刷墙地固 | F9: 1.刷墙地固工艺：清扫地面墙面→安全防范→准备喷涂工具→墙地面全部喷涂→细部涂刷修补→地面涂刷延墙面往上100mm→施工自检； 2.合格标准：顶面、墙面、地面满涂墙地固，角落位置涂刷到位，涂刷均匀无漏涂。 | G9: =#REF! -> #REF!
A10: 精放线 | B10: 平米 | C10: 9 | D10: 按合同面积计算 | E10: 放水平线、中轴线、规方线、完成面线、吊顶线、新建墙体线、门洞定位线、点位线等 | F10: 1.精放线标准：包含施工工具准备、放水平线、中轴线、完成面线、吊顶线、新建墙体线、门洞定位线、点位喷漆等。 | G10: =#REF! -> #REF!
A11: 成品保护、铲墙皮、刷墙地固 | B11: 平米 | C11: 52 | D11: 按合同面积计算 | E11: 1.成品保护包含入场检查，电梯厅、走廊、过道、门窗、气表、水表、烟感、可视电话等的保护，管道包隔音棉处理，安全防护 2.铲墙皮（包含墙面和顶面） 3.墙地顶面涂刷界面剂 4.临水临电及精放线等施工准备工作 | F11: 1.成品保护工艺：清扫墙地面→喜鹊字样胶带固定保护膜（电梯间膜、门窗保护膜、燃气表保护罩）→主给排水管道（含天花顶部的存水弯）隔音棉包裹→强弱电箱保护→施工自检； 合格标准：电梯、电梯厅、走廊、门窗、天然气表、强弱电箱等粘贴保护，要求平整方正，方向正确，且无翘脚； 2.安全防护工艺：关闭水电总闸→更换水龙头→接临时电箱→接临时照明→挂阳台安全网防护→施工自检； 合格标准：临时水电做好防漏防渗保护，安全网无漏洞或破损，安全网固定在安全挂钩上，无漏挂，安全网牢固无松动现象； 3.铲墙皮工艺：断水断电→接通临水临电→喷水枪湿润墙面反复3次→铲刀铲除白灰→施工自检；（不含保温层、外墙砖等的拆除） 合格标准：白灰剔除干净，能看见水泥基层，墙面剔除达率到95%以上； 4.刷墙地固工艺：清扫地面墙面→安全防范→准备喷涂工具→墙地面全部喷涂→细部涂刷修补→地面涂刷延墙面往上100mm→施工自检； 合格标准：顶面、墙面、地面满涂墙地固，角落位置涂刷到位，涂刷均匀无漏涂； 5.精放线标准：包含施工工具准备、放水平线、中轴线、完成面线、吊顶线、新建墙体线、门洞定位线、点位喷漆等。 | G11: =#REF! -> #REF!
A12: 成品保护、刷墙地固 | B12: 平米 | C12: 44 | D12: 按合同面积计算 | E12: 1.成品保护包含入场检查，电梯厅、走廊、过道、门窗、气表、水表、烟感、可视电话等的保护，管道包隔音棉处理，安全防护 2.墙地顶面刷界面剂 3.临水临电及精放线等施工准备工作 | F12: 1.成品保护工艺：清扫墙地面→喜鹊字样胶带固定保护膜（电梯间膜、门窗保护膜、燃气表保护罩）→主给排水管道（含天花顶部的存水弯）隔音棉包裹→强弱电箱保护→施工自检； 合格标准：电梯、电梯厅、走廊、门窗、天然气表、强弱电箱等粘贴保护，要求平整方正，方向正确，且无翘脚； 2.安全防护工艺：关闭水电总闸→更换水龙头→接临时电箱→接临时照明→挂阳台安全网防护→施工自检； 合格标准：临时水电做好防漏防渗保护，安全网无漏洞或破损，安全网固定在安全挂钩上，无漏挂，安全网牢固无松动现象； 3.刷墙地固工艺：清扫地面墙面→安全防范→准备喷涂工具→墙地面全部喷涂→细部涂刷修补→地面涂刷延墙面往上100mm→施工自检 合格标准：顶面、墙面、地面满涂墙地固，角落位置涂刷到位，涂刷均匀无漏涂； 4.精放线标准：包含施工工具准备、放水平线、中轴线、完成面线、吊顶线、新建墙体线、门洞定位线、点位喷漆等。 | G12: =#REF! -> #REF!
A13: 墙体拆除（120墙） | B13: 平米 | C13: 70 | D13: 按拆除面积计算，厚度超出部分按比例折算 | E13: 拆除120墙体 | F13: 1.工艺：核对图纸→放线定位→根据拆除线使用切割机切割后拆除→建渣装袋→清理现场→施工自检； 2.合格标准：打拆前用角磨机先进行切割(防止二次空鼓)；拆除彻底，不残留不遗漏；现场垃圾清理干净，5S维护。 | G13: =#REF! -> #REF!
A14: 墙体拆除（240墙） | B14: 平米 | C14: 85 | D14: 按拆除面积计算，厚度超出部分按比例折算 | E14: 拆除240墙体 | F14: 1.工艺：核对图纸→放线定位→根据拆除线使用切割机切割后拆除→建渣装袋→清理现场→施工自检； 2.合格标准：打拆前用角磨机先进行切割(防止二次空鼓)；拆除彻底，不残留不遗漏；现场垃圾清理干净，5S维护。 | G14: =#REF! -> #REF!
A15: 拆除保温层 | B15: 平米 | C15: 25 | D15: 按拆除面积计算 | E15: 拆除保温层或外墙漆 | F15: 1.工艺：核对图纸→放线定位→（人工+机械）拆除→建渣装袋→清理现场→施工自检； 2.合格标准：打拆前用角磨机先进行切割(防止二次空鼓)；拆除彻底，不残留不遗漏；现场垃圾清理干净，5S维护。 | G15: =#REF! -> #REF!
... A42: 新建360墙（轻质砖） | B42: 平米 | C42: 450 | D42: 按新建面积计算 主要用于厨卫及生活阳台以外的非承重区域 | E42: 包含铲墙皮、植筋、墙体砌筑、新旧墙体交接处挂网、墙面抹灰 | F42: 1.工艺：定位放线→砂浆制拌→砌砖→勾缝、清理→墙面抹灰→施工自检（依据GB50203-2011《砌体工程施工质量验收规范》） 2.合格标准：墙体砖必须错缝1/3修砌、墙体底部以原始地面为基准线砌3层实心砖打底、如湿区墙体在沉箱内的则实心砖打底平齐客厅地面后再往上做3层实心砖、距离顶面80mm-150mm做斜砖蜈蚣脚、墙体间隔500mm做植筋、新旧墙面交界处做挂网处理（网面宽度150mm-200mm）、墙面平整垂直度≤4mm； | G42: =#REF! -> #REF!
A43: 新建单边门垛（200mm宽以内） | B43: 个 | C43: 200 | D43: 按个数计算 | E43: 包含植筋、墙体砌筑、新旧墙体交接处挂网 | F43: 0 | G43: =#REF! -> #REF!
A44: 门窗洞修补（水泥砂浆） | B44: 个 | C44: 150 | D44: 按个数计算 | E44: 水泥砂浆抹灰修补，适用于打拆后的门窗洞修补，不含过梁 | F44: 1.工艺：定位放线→砂浆制拌→砌砖（多孔砖、实心砖、空心砖、加气砖等）→勾缝、清理→施工自检（依据GB50203-2011《砌体工程施工质量验收规范》） 2.合格标准：墙体砖必须错缝1/3修砌、墙体底部以原始地面为基准线砌3层实心砖打底、如湿区墙体在沉箱内的则实心砖打底平齐客厅地面后再往上做3层实心砖、距离顶面80mm-150mm做斜砖蜈蚣脚、墙体间隔500mm做植筋、新旧墙面交界处做挂网处理（网面宽度150mm-200mm）、修补后垂直度误差≤5mm。 | G44: =#REF! -> #REF!
A45: 断面修补 | B45: 米 | C45: 40 | D45: 按延长米数计算 | E45: 0 | F45: 0 | G45: =#REF! -> #REF!
A46: 门过梁施工（1.2米） | B46: 根 | C46: 90 | D46: 按根数计算，墙厚140mm以内的墙使用1根，墙厚>140mm的墙使用2根 | E46: 门洞宽900mm以内 | F46: 1.测量定位→成品过梁安装→水泥砂浆固定→施工自检； 2.合格标准：过梁嵌入墙体两侧分别至少100mm。 | G46: =#REF! -> #REF!
A47: 门过梁施工（1.5米） | B47: 根 | C47: 100 | D47: 按根数计算，墙厚140mm以内的墙使用1根，墙厚>140mm的墙使用2根 | E47: 门洞宽1200mm以内 | F47: 1.测量定位→成品过梁安装→水泥砂浆固定→施工自检； 2.合格标准：过梁嵌入墙体两侧分别至少100mm。 | G47: =#REF! -> #REF!
A48: 门过梁施工（2米） | B48: 根 | C48: 110 | D48: 按根数计算，墙厚140mm以内的墙使用1根，墙厚>140mm的墙使用2根 | E48: 门洞宽1600mm以内 | F48: 1.测量定位→成品过梁安装→水泥砂浆固定→施工自检； 2.合格标准：过梁嵌入墙体两侧分别至少100mm。 | G48: =#REF! -> #REF!
A49: 门钢架过梁施工（3米） | B49: 根 | C49: 150 | D49: 按根数计算，墙厚140mm以内的墙使用1根，墙厚>140mm的墙使用2根 | E49: 门洞宽度大于2米小于2.6米的 | F49: 1.测量定位→L角钢架过梁安装→固定→施工自检； 2.合格标准：过梁嵌入墙体两侧分别至少100mm。 | G49: =#REF! -> #REF!
A50: 空鼓拆除及修复 | B50: 平米 | C50: 75 | D50: 单处空鼓面积小于1㎡按1㎡计算，大于1㎡按实际面积计算 | E50: 空鼓拆除及修复处理等 | F50: 1.工艺：切割机切割墙皮→剔除抹灰面层→水泥砂浆粗找平→施工自检； 2.合格标准：割墙皮应横平竖直切（防止引发周边墙皮松动空鼓）、剔除抹灰层至砖体，要求抹灰层剔除干净能看见砖墙基层，墙面剔除达率到95%以上；现场垃圾清理干净，5S维护，修复完成后墙面抹灰垂直度≤3mm，平整度≤4mm。 | G50: =#REF! -> #REF!
A51: 原建筑补烂修复 | B51: 平米 | C51: 50 | D51: 按施工面积计算 | E51: 打拆之后的门窗洞及墙地面用水泥砂浆抹平，或剔除最高点后修复处理等 | F51: 1.工艺： 湿区空鼓修复：在墙面标注需剔除空鼓的位置→切割拆除→涂刷瓷砖胶→水泥砂浆找平修复→现场清理→施工自检； 干区空鼓修复：在墙面标注需剔除空鼓的位置→切割拆除→涂刷界面剂→石膏找平修复→现场清理→施工自检； 2.合格标准：完成面平整度标准≤2mm。 | G51: =#REF! -> #REF!
A52: 新建壁龛 | B52: 格 | C52: 100 | D52: 按个数计算 | E52: 包含墙体砌筑、新旧墙体交接处挂网 | F52: 0 | G52: =#REF! -> #REF!
A53: 浴缸基座（砌体） | B53: 个 | C53: 1980 | D53: 2米以内按个数计算 超出部分按150元/10cm计算 | E53: 新建浴缸基座+抹灰+涂刷防水涂料+预留检修口（面材的主材和施工单独计算，不含浴缸的供应安装） | F53: 1.工艺：定位放线→砂浆制拌→砌砖→抹灰→防水→现场清理→施工自检； 2.合格标准：符合施工图要求，预留检修口。 | G53: =#REF! -> #REF!
A54: 浴缸基座（钢架） | B54: 个 | C54: 2450 | D54: 2米以内按个数计算 超出部分按200元/10cm计算 | E54: 焊接浴缸钢架基座+涂刷防锈漆+涂刷防水涂料+预留检修口（面材的主材和施工单独计算，不含浴缸的供应安装） | F54: 1.工艺：定位放线→钢管裁切、焊接→自攻螺丝封板→涂刷防锈漆→预留检修口→现场清理→施工自检； 2.合格标准：符合施工图要求，预留检修口。 | G54: =#REF! -> #REF!
A55: 浴缸基座及安装（三面靠墙） | B55: 个 | C55: 4800 | D55: 2米以内按个数计算 超出部分按300元/10cm计算 | E55: 砌砖墙+抹灰+检修口+贴石材（标配石材）+人工+浴缸安装（不含浴缸的供应） | F55: 1.工艺：定位放线→钢管裁切、焊接→自攻螺丝封板→涂刷防锈漆→预留检修口→瓷砖或石材饰面施工→浴缸安装→现场清理→施工自检； 2.合格标准：符合施工图要求，预留检修口，墙面垂直度≤2mm，平整度≤3mm，浴缸安装水平，浴缸与墙面交界处用半透明胶打胶处理，打胶均匀美观，浴缸满水试验无漏水现象。 | G55: =#REF! -> #REF!
A56: 浴缸基座及安装（两面靠墙） | B56: 个 | C56: 5600 | D56: 2米以内按个数计算 超出部分按400元/10cm计算 | E56: 砌砖墙+抹灰+检修口+贴石材（标配石材）+人工+浴缸安装（不含浴缸的供应） | F56: 1.工艺：定位放线→钢管裁切、焊接→自攻螺丝封板→涂刷防锈漆→预留检修口→瓷砖或石材饰面施工→浴缸安装→现场清理→施工自检； 2.合格标准：符合施工图要求，预留检修口，墙面垂直度≤2mm，平整度≤3mm，浴缸安装水平，浴缸与墙面交界处用半透明胶打胶处理，打胶均匀美观，浴缸满水试验无漏水现象。 | G56: =#REF! -> #REF!
A57: 平层水电半改（PPR) | B57: 平米 | C57: 139 | D57: 按合同面积计算，超出标准部分，费用计算规则详见《水电计价标准》 | E57: 包含开槽、开孔、强弱电改造、空开关调试、给排水改造、通水通电测试等 | F57: 1.施工工艺： 开槽开孔：定位→开剔槽→机械开孔→清理→线槽清扫→涂刷界面剂→水泥砂浆或石膏补槽（潮湿位置必须使用水泥砂浆）→表面粘贴专用玻纤网抗裂； 强电改造：定位→PVC塑料线管加工→管道插接固定→穿塑铜线→绝缘导通检验； 弱电改造：定位→PVC塑料线管加工→固定连接→穿单根超五类网络线、光纤线、音箱线、可视线→导通检验； 强弱电箱：空气开关调试、强强弱电线路嵌入箱体； 给水管改造：定位→PP-R管道加工裁切→热熔连接固定→压力测试； 排水管改造：定位→PVC管道加工裁切→连接固定→通排测试。 2.合格标准：管线走向横平竖直，转角处走圆弧弯或S弯。 3.材料包含：阻燃电线、PVC线管、PPR给水管、PVC排水管、底盒等。 | G57: =#REF! -> #REF!
A58: 复式水电半改（PPR) | B58: 平米 | C58: 169 | D58: 按合同面积计算，超出标准部分，费用计算规则详见《水电计价标准》 | E58: 包含开槽、开孔、强弱电改造、空开关调试、给排水改造、通水通电测试等 | F58: 1.施工工艺： 开槽开孔：定位→开剔槽→机械开孔→清理→线槽清扫→涂刷界面剂→水泥砂浆或石膏补槽（潮湿位置必须使用水泥砂浆）→表面粘贴专用玻纤网抗裂； 强电改造：定位→PVC塑料线管加工→管道插接固定→穿塑铜线→更换空开→绝缘导通检验； 弱电改造：定位→PVC塑料线管加工→固定连接→穿单根超五类网络线、光纤线、音箱线、可视线→导通检验； 强弱电箱：空气开关调试、强弱电线路嵌入箱体； 德国TECE给水系统：定位→墙面开槽机顺直线切割开槽→顶面打孔穿管→管路排管一管到底无接头→管路施工走天→厨卫顶面做冷热水分水器→管口采用插接方式施工→压力测试； 排水管改造：定位→PVC管道加工裁切→连接固定→通排测试。 2.合格标准：管线走向横平竖直，转角处走圆弧弯或S弯。 3.材料包含：阻燃电线、PVC线管、PPR给水管、进口TECE一管到底给水管、分集水器、专用管件、PVC排水管、底盒等。 | G58: =#REF! -> #REF!
A59: 平层水电全改（PPR） | B59: 平米 | C59: 259 | D59: 按合同面积计算，超出标准部分，费用计算规则详见《水电计价标准》 | E59: 包含开槽、开孔、强弱电改造、空开关调试、给排水改造、通水通电测试等 | F59: 1.施工工艺： 开槽开孔：定位放线→开剔槽→机械开孔→清理→线槽清扫→水泥砂浆或石膏补槽（潮湿位置必须使用水泥砂浆）→表面粘贴专用玻纤网抗裂。 强电改造：定位→PVC塑料线管加工→管道插接固定→穿塑铜线→并头→烫锡→缠绕PVC绝缘胶带和绝缘胶布→更换空开→绝缘导通检验。 弱电改造：定位→PVC塑料线管加工→固定连接→穿单根超五类网络线、光纤线、音箱线、可视线→导通检验。 强弱电箱移位：人工进行测量定位→弹线→机械开孔→设置过梁→强弱电箱安装→空气开关安装调试、强弱电线路嵌入箱体 给水管改造：定位→PP-R管道加工裁切→热熔连接固定→压力测试 排水管改造：定位→PVC管道加工裁切→连接固定→通排测试，沉箱内必须做暗漏。 2.合格标准：管线走向横平竖直，转角处走圆弧弯或S弯。 3.材料包含：阻燃电线、PVC线管、PPR给水管、PVC排水管、底盒等； | G59: =#REF! -> #REF!
A60: 复式水电全改（PPR） | B60: 平米 | C60: 299 | D60: 按合同面积计算，超出标准部分，费用计算规则详见《水电计价标准》 | E60: 包含开槽、开孔、强弱电改造、空开关调试、给排水改造、通水通电测试等 | F60: 1.施工工艺： 开槽开孔：定位放线→开剔槽→机械开孔→清理→线槽清扫→水泥砂浆或石膏补槽（潮湿位置必须使用水泥砂浆）→表面粘贴专用玻纤网抗裂。 强电改造：定位→PVC塑料线管加工→管道插接固定→穿塑铜线→并头→烫锡→缠绕PVC绝缘胶带和绝缘胶布→更换空开→绝缘导通检验。 弱电改造：定位→PVC塑料线管加工→固定连接→穿单根超五类网络线、光纤线、音箱线、可视线→导通检验。 强弱电箱移位：人工进行测量定位→弹线→机械开孔→设置过梁→强弱电箱安装→空气开关安装调试、强弱电线路嵌入箱体 给水管改造：定位→PP-R管道加工裁切→热熔连接固定→压力测试 排水管改造：定位→PVC管道加工裁切→连接固定→通排测试，沉箱内必须做暗漏。 2.合格标准：管线走向横平竖直，转角处走圆弧弯或S弯。 3.材料包含：阻燃电线、PVC线管、PPR给水管、PVC排水管、底盒等； | G60: =#REF! -> #REF!
A61: 别墅水电全改（PPR） | B61: 平米 | C61: 299 | D61: 按合同面积计算，超出标准部分，费用计算规则详见《水电计价标准》 | E61: 包含开槽、开孔、强弱电改造、空开关调试、给排水改造、通水通电测试等 | F61: 1.施工工艺： 开槽开孔：定位放线→开剔槽→机械开孔→清理→线槽清扫→水泥砂浆或石膏补槽（潮湿位置必须使用水泥砂浆）→表面粘贴专用玻纤网抗裂。 强电改造：定位→PVC塑料线管加工→管道插接固定→穿塑铜线→并头→烫锡→缠绕PVC绝缘胶带和绝缘胶布→更换空开→绝缘导通检验。 弱电改造：定位→PVC塑料线管加工→固定连接→穿单根超五类网络线、光纤线、音箱线、可视线→导通检验。 强弱电箱移位：人工进行测量定位→弹线→机械开孔→设置过梁→强弱电箱安装→空气开关安装调试、强弱电线路嵌入箱体 给水管改造：定位→PP-R管道加工裁切→热熔连接固定→压力测试 排水管改造：定位→PVC管道加工裁切→连接固定→通排测试，沉箱内必须做暗漏。 2.合格标准：管线走向横平竖直，转角处走圆弧弯或S弯。 3.材料包含：阻燃电线、PVC线管、PPR给水管、PVC排水管、底盒等； | G61: =#REF! -> #REF!
A62: 平层水电全改（进口PPR） | B62: 平米 | C62: 289 | D62: 按合同面积计算，超出标准部分，费用计算规则详见《水电计价标准》 | E62: 包含开槽、开孔、强弱电改造、空开关调试、给排水改造、通水通电测试等 | F62: 1.施工工艺： 开槽开孔：定位放线→开剔槽→机械开孔→清理→线槽清扫→水泥砂浆或石膏补槽（潮湿位置必须使用水泥砂浆）→表面粘贴专用玻纤网抗裂。 强电改造：定位→PVC塑料线管加工→管道插接固定→穿塑铜线→并头→烫锡→缠绕PVC绝缘胶带和绝缘胶布→更换空开→绝缘导通检验。 弱电改造：定位→PVC塑料线管加工→固定连接→穿单根超五类网络线、光纤线、音箱线、可视线→导通检验。 强弱电箱移位：人工进行测量定位→弹线→机械开孔→设置过梁→强弱电箱安装→空气开关安装调试、强弱电线路嵌入箱体 给水管改造：定位→PP-R管道加工裁切→热熔连接固定→压力测试 排水管改造：定位→PVC管道加工裁切→连接固定→通排测试，沉箱内必须做暗漏。 2.合格标准：管线走向横平竖直，转角处走圆弧弯或S弯。 3.材料包含：阻燃电线、PVC线管、PPR给水管、PVC排水管、底盒等； | G62: =#REF! -> #REF!
A63: 复式水电全改（进口PPR） | B63: 平米 | C63: 339 | D63: 按合同面积计算，超出标准部分，费用计算规则详见《水电计价标准》 | E63: 包含开槽、开孔、强弱电改造、空开关调试、给排水改造、通水通电测试等 | F63: 1.施工工艺： 开槽开孔：定位放线→开剔槽→机械开孔→清理→线槽清扫→水泥砂浆或石膏补槽（潮湿位置必须使用水泥砂浆）→表面粘贴专用玻纤网抗裂。 强电改造：定位→PVC塑料线管加工→管道插接固定→穿塑铜线→并头→烫锡→缠绕PVC绝缘胶带和绝缘胶布→更换空开→绝缘导通检验。 弱电改造：定位→PVC塑料线管加工→固定连接→穿单根超五类网络线、光纤线、音箱线、可视线→导通检验。 强弱电箱移位：人工进行测量定位→弹线→机械开孔→设置过梁→强弱电箱安装→空气开关安装调试、强弱电线路嵌入箱体 给水管改造：定位→PP-R管道加工裁切→热熔连接固定→压力测试 排水管改造：定位→PVC管道加工裁切→连接固定→通排测试，沉箱内必须做暗漏。 2.合格标准：管线走向横平竖直，转角处走圆弧弯或S弯。 3.材料包含：阻燃电线、PVC线管、PPR给水管、PVC排水管、底盒等； | G63: =#REF! -> #REF!
A64: 别墅水电全改（进口PPR） | B64: 平米 | C64: 339 | D64: 按合同面积计算，超出标准部分，费用计算规则详见《水电计价标准》 | E64: 包含开槽、开孔、强弱电改造、空开关调试、给排水改造、通水通电测试等 | F64: 1.施工工艺： 开槽开孔：定位放线→开剔槽→机械开孔→清理→线槽清扫→水泥砂浆或石膏补槽（潮湿位置必须使用水泥砂浆）→表面粘贴专用玻纤网抗裂。 强电改造：定位→PVC塑料线管加工→管道插接固定→穿塑铜线→并头→烫锡→缠绕PVC绝缘胶带和绝缘胶布→更换空开→绝缘导通检验。 弱电改造：定位→PVC塑料线管加工→固定连接→穿单根超五类网络线、光纤线、音箱线、可视线→导通检验。 强弱电箱移位：人工进行测量定位→弹线→机械开孔→设置过梁→强弱电箱安装→空气开关安装调试、强弱电线路嵌入箱体 给水管改造：定位→PP-R管道加工裁切→热熔连接固定→压力测试 排水管改造：定位→PVC管道加工裁切→连接固定→通排测试，沉箱内必须做暗漏。 2.合格标准：管线走向横平竖直，转角处走圆弧弯或S弯。 3.材料包含：阻燃电线、PVC线管、PPR给水管、PVC排水管、底盒等； | G64: =#REF! -> #REF!
... A204: 单层石膏板基层 | B204: 平米 | C204: 88 | D204: 按施工面积计算 | E204: 包含石膏板基层施工 | F204: 1.工艺：测量、定位→板材封面（石膏板）→施工自检； 2.合格标准：平整度误差3mm以内，垂直度误差2mm以内。 | G204: =#REF! -> #REF!
A205: 石膏板水缝拉槽处理 | B205: 米 | C205: 16 | D205: 按延长米计算 | E205: 包含基层拉槽处理等 | F205: 0 | G205: =#REF! -> #REF!
A206: 单层石膏板基层+拉槽处理 | B206: 平米 | C206: 158 | D206: 按施工面积计算 | E206: 包含石膏板基层施工及留缝处理 | F206: 1.工艺：测量、定位→板材封面（石膏板）、留缝处理→施工自检； 2.合格标准：平整度误差3mm以内，垂直度误差2mm以内。 | G206: =#REF! -> #REF!
A207: 嵌入式踢脚线木基层（含开槽） | B207: 平米 | C207: 75 | D207: 按延长米计算 | E207: 包含墙面开槽、木基层封板调平 | F207: 1.工艺：测量、定位→开槽→板材封面（阻燃板）→施工自检； 2.合格标准：平整度误差3mm以内，垂直度误差2mm以内。 | G207: =#REF! -> #REF!
A208: 嵌入式踢脚线木基层（不含开槽） | B208: 平米 | C208: 48 | D208: 按延长米计算 | E208: 包含木基层封板调平 | F208: 1.工艺：测量、定位→板材封面（阻燃板）→施工自检； 2.合格标准：平整度误差3mm以内，垂直度误差2mm以内。 | G208: =#REF! -> #REF!
A209: 冲筋 | B209: 平米 | C209: 35 | D209: 按合同面积计算 | E209: 放线、定位、冲大面筋、冲阴阳角筋、横阳筋等 | F209: 1.工艺：水平仪校正放规方线→在墙面冲找平筋条（间距≤1200mm）→阴阳角区域处理→施工自检→养护； 2.合格标准：以筋平面为石膏找平完成面，使用2400mm靠尺检查墙面平整度，平整度误差≤3mm，阴阳角方正。 | G209: =#REF! -> #REF! | H209: 套餐升级价格
A210: 墙面冲筋做方正 | B210: 平米 | C210: 50 | D210: 按墙面面积计算 | E210: 放线、定位、冲大面筋、冲阴阳角筋、横阳筋、石膏找平等 | F210: 1.工艺：水平仪校正放规方线→在墙面冲找平筋条（间距≤1200mm）→阴阳角区域处理→人工涂刷界面剂一遍→基层处理（挂网、补钉眼、贴纸胶带）→石膏配合筋条进行墙面精找平→靠尺赶平→批刮腻子两遍→灯照砂纸打磨→底漆一遍→施工自检→养护； 2.合格标准：以筋平面为石膏找平完成面，使用2400mm靠尺检查墙面平整度，平整度误差≤3mm，阴阳角方正； 3.包含墙面线槽修补、刷界面剂、冲筋、挂网、石膏找方正、阴阳角处理、两遍腻子找平、打磨、一遍底漆施工等。 | G210: =#REF! -> #REF! | H210: 套餐升级价格
A211: 墙面石膏腻子顺平处理(干区) | B211: 平米 | C211: 58 | D211: 按施工面积计算，门窗面积按50%计算 | E211: 刷界面剂、挂网、补钉眼、铲胶、贴纸胶带、石膏找平、阴阳角处理、两遍腻子施工、打磨和一遍底漆施工等 | F211: 1.工艺：人工涂刷界面剂一遍→基层处理（挂网、补钉眼、贴纸胶带）→石膏涂抹上墙→靠尺赶平→批刮腻子两遍→灯照砂纸打磨→底漆或基膜一遍→施工自检→养护； 2.合格标准：找平完成面平整度误差5mm以内； 3.包含线槽修补、刷界面剂、挂网、补钉眼、贴纸胶带、石膏找平、阴阳角处理、两遍腻子找平、打磨、一遍底漆施工等。 | G211: =#REF! -> #REF!
A212: 墙面石膏腻子顺平处理(湿区) | B212: 平米 | C212: 58 | D212: 按施工面积计算，门窗面积按50%计算 | E212: 刷界面剂、挂网、补钉眼、铲胶、贴纸胶带、石膏找平、阴阳角处理、两遍腻子施工、打磨和一遍底漆施工等 | F212: 1.工艺：人工涂刷界面剂一遍→基层处理（挂网、补钉眼、贴纸胶带）→石膏涂抹上墙→靠尺赶平→批刮腻子两遍→灯照砂纸打磨→底漆或基膜一遍→施工自检→养护； 2.合格标准：找平完成面平整度误差5mm以内； 3.包含线槽修补、刷界面剂、挂网、补钉眼、贴纸胶带、石膏找平、阴阳角处理、两遍腻子找平、打磨、一遍底漆施工等。 | G212: =#REF! -> #REF!
A213: 顶面石膏腻子顺平处理（干区） | B213: 平米 | C213: 58 | D213: 按施工面积计算，门窗面积按50%计算 | E213: 刷界面剂、挂网、补钉眼、铲胶、贴纸胶带、石膏找平、阴阳角处理、两遍腻子施工、打磨和一遍底漆施工等 | F213: 1.工艺：人工涂刷界面剂一遍→基层处理（挂网、补钉眼、贴纸胶带）→石膏涂抹→靠尺赶平→批刮腻子两遍→灯照砂纸打磨→底漆一遍→施工自检→养护； 2.合格标准：找平完成面平整度误差5mm以内； 3.包含线槽修补、刷界面剂、挂网、补钉眼、贴纸胶带、石膏找平、阴阳角处理、两遍腻子找平、打磨、一遍底漆施工等。 | G213: =#REF! -> #REF!
A214: 顶面石膏腻子顺平处理（湿区） | B214: 平米 | C214: 58 | D214: 按施工面积计算，门窗面积按50%计算 | E214: 刷界面剂、挂网、补钉眼、铲胶、贴纸胶带、石膏找平、阴阳角处理、两遍腻子施工、打磨和一遍底漆施工等 | F214: 1.工艺：人工涂刷界面剂一遍→基层处理（挂网、补钉眼、贴纸胶带）→石膏涂抹→靠尺赶平→批刮腻子两遍→灯照砂纸打磨→底漆一遍→施工自检→养护； 2.合格标准：找平完成面平整度误差5mm以内； 3.包含线槽修补、刷界面剂、挂网、补钉眼、贴纸胶带、石膏找平、阴阳角处理、两遍腻子找平、打磨、一遍底漆施工等。 | G214: =#REF! -> #REF!
A215: 墙面基层冲筋做方正找平（干区） | B215: 平米 | C215: 108 | D215: 按施工面积计算，门窗面积按50%计算 | E215: 刷界面剂、冲筋、挂网、补钉眼、铲胶、贴纸胶带、石膏找平、阴阳角处理、两遍腻子施工、打磨和一遍底漆施工等 | F215: 1.工艺：水平仪校正放规方线→在墙面冲找平筋条（间距≤1200mm）→阴阳角区域处理→人工涂刷界面剂一遍→基层处理（挂网、补钉眼、贴纸胶带）→石膏配合筋条进行墙面精找平→靠尺赶平→批刮腻子两遍→灯照砂纸打磨→底漆一遍→施工自检→养护； 2.合格标准：以筋平面为石膏找平完成面，使用2400mm靠尺检查墙面平整度，平整度误差≤3mm，阴阳角方正； 3.包含墙面线槽修补、刷界面剂、冲筋、挂网、石膏找方正、阴阳角处理、两遍腻子找平、打磨、一遍底漆施工等。 | G215: =#REF! -> #REF!
A216: 墙面基层冲筋做方正找平（湿区） | B216: 平米 | C216: 108 | D216: 按施工面积计算，门窗面积按50%计算 | E216: 刷界面剂、冲筋、挂网、补钉眼、铲胶、贴纸胶带、石膏找平、阴阳角处理、两遍腻子施工、打磨和一遍底漆施工等 | F216: 1.工艺：水平仪校正放规方线→在墙面冲找平筋条（间距≤1200mm）→阴阳角区域处理→人工涂刷界面剂一遍→基层处理（挂网、补钉眼、贴纸胶带）→石膏配合筋条进行墙面精找平→靠尺赶平→批刮腻子两遍→灯照砂纸打磨→底漆一遍→施工自检→养护； 2.合格标准：以筋平面为石膏找平完成面，使用2400mm靠尺检查墙面平整度，平整度误差≤3mm，阴阳角方正； 3.包含墙面线槽修补、刷界面剂、冲筋、挂网、石膏找方正、阴阳角处理、两遍腻子找平、打磨、一遍底漆施工等。 | G216: =#REF! -> #REF!
A217: 墙面基层冲筋做方正找平（加厚10mm） | B217: 平米 | C217: 146 | D217: 按施工面积计算，门窗面积按50%计算 | E217: 刷界面剂、挂网、补钉眼、铲胶、贴纸胶带、石膏找平、阴阳角处理、两遍腻子施工、打磨和一遍底漆施工等 | F217: 1.工艺：水平仪校正放规方线→在墙面冲找平筋条（间距≤1200mm）→阴阳角区域处理→人工涂刷界面剂一遍→基层处理（挂网、补钉眼、贴纸胶带）→石膏配合筋条进行墙面精找平→靠尺赶平→批刮腻子两遍→灯照砂纸打磨→底漆一遍→施工自检→养护； 2.合格标准：以筋平面为石膏找平完成面，使用2400mm靠尺检查墙面平整度，平整度误差≤3mm，阴阳角方正； 3.包含墙面线槽修补、刷界面剂、冲筋、挂网、石膏找方正、阴阳角处理、两遍腻子找平、打磨、一遍底漆施工等。 | G217: =#REF! -> #REF!
A218: 吊顶直角边线倒圆弧处理 | B218: 米 | C218: 98 | D218: 按延长米计算 | E218: 直角倒圆角处理、打磨、石膏腻子基层、打磨和一遍底漆施工 | F218: 1.工艺：直角打磨倒圆角处理→基层处理（挂网、贴纸胶带）→石膏涂抹→刮平→批刮腻子两遍→灯照砂纸打磨→底漆或基膜一遍→施工自检→养护； 2.合格标准：找平完成面垂直平整度误差3mm以内； 3.包含倒角、刷界面剂、挂网、补钉眼、贴纸胶带、石膏找平、阴阳角处理、两遍腻子找平、打磨、一遍底漆施工等。 | G218: =#REF! -> #REF!
A219: 墙面直角倒圆弧处理 | B219: 米 | C219: 98 | D219: 按延长米计算 | E219: 直角倒圆角处理、打磨、石膏腻子基层、打磨和一遍底漆施工 | F219: 1.工艺：直角打磨倒圆角处理→基层处理（挂网、贴纸胶带）→石膏涂抹→刮平→批刮腻子两遍→灯照砂纸打磨→底漆或基膜一遍→施工自检→养护； 2.合格标准：找平完成面垂直平整度误差3mm以内； 3.包含倒角、刷界面剂、挂网、补钉眼、贴纸胶带、石膏找平、阴阳角处理、两遍腻子找平、打磨、一遍底漆施工等。 | G219: =#REF! -> #REF!
A220: 石膏线修补 | B220: 米 | C220: 6 | D220: 按延长米计算 | E220: 线条处理、打磨、石膏腻子基层、打磨和一遍底漆施工 | F220: 1.工艺：线条打磨处理→基层处理（挂网、贴纸胶带）→石膏涂抹→刮平→批刮腻子两遍→灯照砂纸打磨→底漆或基膜一遍→施工自检→养护； 2.合格标准：找平完成面垂直平整度误差3mm以内； 3.包含倒角、刷界面剂、挂网、补钉眼、贴纸胶带、石膏找平、阴阳角处理、两遍腻子找平、打磨、一遍底漆施工等。 | G220: =#REF! -> #REF!
A221: 精修、打胶收口 | B221: 平米 | C221: 8 | D221: 按合同面积计算 | E221: 施工结束后由专业乳胶漆、艺术漆涂装公司进行精修 | F221: 1.对室内墙顶面受损部位进行漆面修补一次，按面漆涂刷施工工艺施工； 注意：踢脚线、阴阳角、窗边、门边、开孔周围等区域着重修补。 | G221: =#REF! -> #REF!
A222: 水泥河沙贴地砖（600*1200） | B222: 平米 | C222: 140 | D222: 按施工面积计算 | E222: 水泥砂浆贴砖，含瓷砖加工、缝隙清理、瓷砖面清理、勾缝、地面贴保护膜等 | F222: 1.工艺：基层清理→水平仪定位、放线→材料预排版→清理瓷砖表面、浸泡→墙地面洒水润湿→制拌砂浆→铺贴、勾缝→养护及现场清理→施工自检； 2.合格标准：垂直平整度误差5mm以内，4片砖对接处手触摸无凹凸感，无空鼓，边角横向不能有100mm以内小条，竖向不能有50mm以内小条；柜体台面安装阴阳角800mm-1000mm位置范围处直角度确保90°； 3.包含施工完成后的瓷砖表面清理、专用保护膜保护等； 4.不含美缝。 | G222: =#REF! -> #REF!
... A239: 瓷砖拼花 | B239: 平米 | C239: 385 | D239: 按施工面积计算 | E239: 瓷砖拼花施工 | F239: 1.工艺：清理瓷砖表面→墙面找平层检查→水泥扫浆→测量定位→材料预排→标高定位→瓷砖胶泥搅拌→批刮胶泥→瓷砖薄贴、勾缝、阳角加工处理→养护及现场清理→施工自检； 2.合格标准：垂直平整度达到垂2平3，4片砖对接处手触摸无凹凸感，无空鼓，边角横向不能有100mm以内小条，竖向不能有50mm以内小条；柜体台面安装阴阳角800mm-1000mm位置范围处直角度确保90°； 3.包含施工完成后的瓷砖表面清理、专用保护膜保护、阳角保护等； 4.不含美缝。 | G239: =#REF! -> #REF!
A240: 弧形区域地砖施工 | B240: 米 | C240: +25 | D240: 按延长米计算 | E240: 瓷砖异型加工及安装 | F240: 1.工艺：清理瓷砖表面→墙面找平层检查→水泥扫浆→测量定位→材料预排→标高定位→瓷砖胶泥搅拌→批刮胶泥→瓷砖粘贴→现场清理→施工自检； 2.合格标准：接缝处高差1mm以内，整条长边误差2mm以内； | G240: =#REF! -> #REF!
A241: 弧形区域瓷砖翻边 | B241: 米 | C241: +25 | D241: 按延长米计算 | E241: 瓷砖异型加工及安装 | F241: 1.工艺：清理瓷砖表面→墙面找平层检查→水泥扫浆→测量定位→材料预排→标高定位→瓷砖胶泥搅拌→批刮胶泥→瓷砖粘贴→现场清理→施工自检； 2.合格标准：接缝处高差1mm以内，整条长边误差2mm以内； | G241: =#REF! -> #REF!
A242: 瓷砖波打线施工 | B242: 米 | C242: +35 | D242: 按延长米计算，最低收费10米 | E242: 瓷砖异型加工及安装 | F242: 1.工艺：清理瓷砖表面→墙面找平层检查→水泥扫浆→测量定位→材料预排→标高定位→瓷砖胶泥搅拌→批刮胶泥→瓷砖粘贴→现场清理→施工自检； 2.合格标准：接缝处高差1mm以内，整条长边误差2mm以内； | G242: =#REF! -> #REF!
A243: 楼梯踏步贴砖 | B243: 步 | C243: 145 | D243: 按踏步数计算，转角平台处算量两步 | E243: 瓷砖胶薄贴法施工，含瓷砖加工、缝隙清理、瓷砖面清理、勾缝、贴保护膜、阳角保护等 | F243: 1.工艺：清理瓷砖表面→墙面找平层检查→水泥扫浆→测量定位→材料预排→标高定位→瓷砖胶泥搅拌→批刮胶泥→瓷砖薄贴、勾缝、阳角加工处理→养护及现场清理→施工自检； 2.合格标准：垂直平整度达到垂2平3，4片砖对接处手触摸无凹凸感，无空鼓；柜体台面安装阴阳角800mm-1000mm位置范围处直角度确保90°； 3.包含施工完成后的瓷砖表面清理、专用保护膜保护、阳角保护等； 4.不含美缝。 | G243: =#REF! -> #REF!
A244: 壁龛（300*300以内） | B244: 格 | C244: 200 | D244: 按壁龛格数计算 | E244: 墙面防水、瓷砖胶薄贴法施工，含瓷砖加工、缝隙清理、瓷砖面清理、阳角保护等 | F244: 1.工艺：清理瓷砖表面→墙面找平层检查→水泥扫浆→测量定位→材料预排→标高定位→瓷砖胶泥搅拌→批刮胶泥→瓷砖薄贴、勾缝、阳角加工处理→养护及现场清理→施工自检； 2.合格标准：垂直平整度达到垂2平3，4片砖对接处手触摸无凹凸感，无空鼓，边角横向不能有100mm以内小条，竖向不能有50mm以内小条；柜体台面安装阴阳角800mm-1000mm位置范围处直角度确保90°； 3.包含施工完成后的瓷砖表面清理、专用保护膜保护、阳角保护等； 4.不含美缝。 | G244: =#REF! -> #REF!
A245: 壁龛(大砖：300mm及以上） | B245: 格 | C245: 150 | D245: 按壁龛格数计算 | E245: 墙面防水、瓷砖胶薄贴法施工，含瓷砖加工、缝隙清理、瓷砖面清理、阳角保护等 | F245: 1.工艺：清理瓷砖表面→墙面找平层检查→水泥扫浆→测量定位→材料预排→标高定位→瓷砖胶泥搅拌→批刮胶泥→瓷砖薄贴、勾缝、阳角加工处理→养护及现场清理→施工自检； 2.合格标准：垂直平整度达到垂2平3，4片砖对接处手触摸无凹凸感，无空鼓，边角横向不能有100mm以内小条，竖向不能有50mm以内小条；柜体台面安装阴阳角800mm-1000mm位置范围处直角度确保90°； 3.包含施工完成后的瓷砖表面清理、专用保护膜保护、阳角保护等； 4.不含美缝。 | G245: =#REF! -> #REF!
A246: 瓷砖胶工艺墙 | B246: 平米 | C246: 99 | D246: 按施工面积计算 | E246: 瓷砖胶工艺展示墙施工 | F246: 1.采用瓷砖胶进行墙面造型处理； | G246: =#REF! -> #REF!
A247: 瓷砖踢脚线（成品踢脚线） | B247: 米 | C247: 30 | D247: 按延长米计算 | E247: 贴瓷砖踢脚线(不含现场切割加工) | F247: 1.工艺：清理瓷砖表面→墙面找平层检查→水泥扫浆→测量定位→材料预排→标高定位→瓷砖胶泥搅拌→批刮胶泥→瓷砖踢脚线粘贴→现场清理→施工自检； 2.合格标准：接缝处高差1mm以内，整条长边误差2mm以内； 3.瓷砖胶粘贴踢脚线。 | G247: =#REF! -> #REF!
A248: 瓷砖踢脚线（非成品类） | B248: 米 | C248: 40 | D248: 按延长米计算 | E248: 贴瓷砖踢脚线(含瓷砖现场切割加工) | F248: 1.工艺：清理瓷砖表面→墙面找平层检查→水泥扫浆→测量定位→材料预排→标高定位→瓷砖胶泥搅拌→批刮胶泥→瓷砖踢脚线加工→粘贴→现场清理→施工自检； 2.合格标准：接缝处高差1mm以内，整条长边误差2mm以内； 3.瓷砖胶粘贴踢脚线。 | G248: =#REF! -> #REF!
A249: 暗藏式瓷砖踢脚线 | B249: 米 | C249: 58 | D249: 按延长米计算 | E249: 包含墙面开槽处理，成品瓷砖踢脚线安装 | F249: 1.工艺：清理瓷砖表面→墙面找平层检查→水泥扫浆→测量定位→材料预排→标高定位→瓷砖胶泥搅拌→批刮胶泥→瓷砖踢脚线粘贴→现场清理→施工自检； 2.合格标准：接缝处高差1mm以内，整条长边误差2mm以内； 3.瓷砖胶粘贴踢脚线。 | G249: =#REF! -> #REF!
A250: 瓷砖填缝升级美缝（卓高） | B250: 平米 | C250: 30 | D250: 按施工面积计算 | E250: 包含清理缝隙、美缝剂、人工施工等 | F250: 1.工艺：清理瓷砖表面→美缝→保护及现场清理→施工自检； 2.合格标准：瓷砖填缝均匀、平滑、无漏填、少填、色差等； 3.包含施工完成后的瓷砖表面清理、专用保护膜保护、阳角保护等。 | G250: =#REF! -> #REF!
A251: 乳胶漆喷涂 | B251: 平米 | C251: 0 | D251: 按施工面积计算 分色费另计 | E251: 面漆喷涂施工 | F251: 1.工艺：面漆喷涂→施工自检； 2.合格标准：完成面颜色均匀，平整度误差5mm以内。 | G251: =#REF! -> #REF!
A252: 乳胶漆滚涂 | B252: 平米 | C252: 15 | D252: 按施工面积计算 分色费另计 | E252: 面漆滚涂施工 | F252: 1.工艺：面漆喷涂→施工自检； 2.合格标准：完成面颜色均匀，平整度误差5mm以内。 | G252: =#REF! -> #REF!
A253: 艺术漆施工 | B253: 平米 | C253: 0 | D253: 按施工面积计算，门窗洞口面积计算50% 两个及以上的颜色费用另计 | E253: 艺术漆施工 | F253: 1.工艺：艺术漆施工→施工自检； 2.合格标准：完成面颜色均匀，平整度误差5mm以内。 | G253: =#REF! -> #REF!
A254: 乳胶漆分色费 | B254: 个 | C254: 120 | D254: 按颜色个数计算，全屋乳胶漆3个色以内免费，3个色以上每增加1个色加100元，异形墙面分色300元/个 | E254: 乳胶漆分色 | F254: 乳胶漆分色 | G254: =#REF! -> #REF!
... A322: 地面石材安装 | B322: 平米 | C322: 165 | D322: 按施工面积计算 | E322: 包含石材铺贴、缝隙清理、石材表面清理等 | F322: 1.工艺：挡水石及门槛石安装：挡水石槽中满填石材粘接剂→砖槽内满铺粘接剂（砖槽深度大于40mm时需先铺一层水泥砂浆），将挡水石嵌入砖槽中压实铺平→根据现场基层情况确认嵌入深度（石材高出瓷砖面40mm）→石材四周留2mm缝隙 2.合格标准：钻石型淋浴房挡水石安装成135°淋浴房挡水石不能压地漏，门槛石高于客厅瓷砖面或者卧室木地板3mm比卫生间砖面高10mm。 | G322: =#REF! -> #REF!
A323: 弧形区域石材翻边 | B323: 米 | C323: +45 | D323: 按延长米计算,最低收费7米 | E323: 石材异型加工及安装 | F323: 1.工艺：清理瓷砖表面→墙面找平层检查→水泥扫浆→测量定位→材料预排→标高定位→大理石胶泥搅拌→批刮胶泥→石材粘贴→现场清理→施工自检； 2.合格标准：接缝处高差1mm以内，整条长边误差2mm以内； | G323: =#REF! -> #REF!
A324: 室内垃圾清理，现场5S | B324: 平米 | C324: 8 | D324: 按合同面积计算 | E324: 包含室内垃圾清理，清运至物业指定地点，现场5S维护等 | F324: 1.仅包含有电梯的小区室内垃圾清理，清运至物业指定地点，现场5S维护等； 2.不含建渣外运及物业特殊要求的建渣处理，如需外运费用另计。 | G324: =#REF! -> #REF!
A325: 建渣集中清理 | B325: 平米 | C325: 10 | D325: 按合同面积计算，最低收费1000元/户 | E325: 适用范围：仅限物业要求需要定时清理建渣到小区内建渣池的项目 | F325: 1.适用范围：仅限物业要求需要定时清理建渣到小区内建渣池的项目。 | G325: =#REF! -> #REF!
A326: 建渣外运（纯建渣） | B326: 车 | C326: 1400 | D326: 按车计算 100平米以内4车，每50平米一个阶梯增加1车。 不含打拆阶段建渣，打拆建渣按打拆数量计算。 | E326: 适用范围：仅限小区内无建渣池客户要求我方外运建渣的项目 | F326: 1.仅限小区内无建渣池的垃圾外运； 2.建渣车数按以下标准计算：150平米以内：6车；200平米以内：8车；200平米以上：10车。 3.特殊情况另行商议。 | G326: =#REF! -> #REF!
A327: 建渣外运（混合建渣） | B327: 车 | C327: 1400 | D327: 按车计算 100平米以内4车，每50平米一个阶梯增加1车。 不含打拆阶段建渣，打拆建渣按打拆数量计算。 | E327: 适用范围：仅限小区内无建渣池客户要求我方外运建渣的项目 | F327: 1.仅限小区内无建渣池的垃圾外运； 2.建渣车数按以下标准计算：150平米以内：6车；200平米以内：8车；200平米以上：10车。 3.特殊情况另行商议。 | G327: =#REF! -> #REF!
A328: 无电梯建渣上下楼搬运费（搬运1层） | B328: 平米 | C328: 6 | D328: 按楼层面积计算 | E328: 仅包含建渣装袋人工搬运至物业指定的小区内建渣池，台阶>3级的需计算费用 | F328: 1.仅包含建渣装袋人工搬运至物业指定的小区内建渣池，台阶>3级的需计算费用。 | G328: =#REF! -> #REF!
A329: 无电梯建渣上下楼搬运费（搬运2-3层） | B329: 平米 | C329: 12 | D329: 按楼层面积计算 | E329: 仅包含建渣装袋人工搬运至物业指定的小区内建渣池，台阶>3级的需计算费用 | F329: 1.仅包含建渣装袋人工搬运至物业指定的小区内建渣池，台阶>3级的需计算费用。 | G329: =#REF! -> #REF!
A330: 无电梯建渣上下楼搬运费（搬运4层以上） | B330: 平米 | C330: 18 | D330: 按楼层面积计算 | E330: 仅包含建渣装袋人工搬运至物业指定的小区内建渣池，台阶>3级的需计算费用 | F330: 1.仅包含建渣装袋人工搬运至物业指定的小区内建渣池，台阶>3级的需计算费用。 | G330: =#REF! -> #REF!
A331: 建渣转运 | B331: 车 | C331: 400 | D331: 按车计算 100平米以内4车，每50平米一个阶梯增加1车。 不含打拆阶段建渣，打拆建渣按打拆数量计算。 | E331: 适用范围： 1）建渣池不在小区内的； 2）无法直接用小推车需要从地下室转运建渣至地面的； 3）小区内无建渣池需要转运至小区外物业制定地点的。 | F331: 1.适用范围： 1）建渣池不在小区内的； 2）无法直接用小推车需要从地下室转运建渣至地面的； 3）小区内无建渣池需要转运至小区外物业制定地点的。 2.建渣车数按以下标准计算：150平米以内：6车；200平米以内：8车；200平米以上：10车。 3.特殊情况另行商议。 | G331: =#REF! -> #REF!
A332: 开荒保洁 | B332: 平米 | C332: 7 | D332: 按合同面积计算 | E332: 对施工现场进行初步清洁，确保现场基本洁净，满足成品安装条件 | F332: 1.门窗保洁：入户门保护膜保留，保护膜、胶、残留物清理，门框凹槽无杂物； 2.墙顶地面保洁：瓷砖保护膜清理、垃圾清理、残留物清理、砖缝里杂物清理，地面石膏、腻子、水泥河沙、凸出物使用铲刀吸尘器清理物料优先放生活阳台，无生活阳台放景观阳台，摆放整齐，垃圾集中装袋处理带走； 注意：保洁施工时务必小心，避免产品碰损、二次污染等，离开前请认真检查门窗、水电是否关好。 | G332: =#REF! -> #REF!
A333: 精保洁 | B333: 平米 | C333: 7 | D333: 按合同面积计算 | E333: 对现场深度清洁，确保清洁完成后现场清洁干净，无灰尘，无污渍，无水渍，达到交付标准 | F333: 1.入户门保护膜清除，表面擦拭干净，无灰尘，无污染，凹凸部位无藏灰，锁眼干净无堵塞； 2.窗框、轨道、纱窗、玻璃、花架清洁干净无灰尘； 3.五金洁具清洁到位表面光亮无污染，能照出人影； 4.门及锁把手清洁到位干净无杂质； 5.墙面踢脚线无灰尘，污渍，涂料点，电源盒里外干净，无杂物，开关面板干净无水渍； 6.室内地面无灰层无杂质无垃圾无污染； 7.室内墙面光亮、干净、用手触摸检查无灰层附着； 8.木地板、瓷砖、台面无灰尘，无水渍，无漆点有光泽等。 | G333: =#REF! -> #REF!
A334: 楼梯防护栏焊接 | B334: 米 | C334: 249 | D334: 按延长米计算 | E334: 一般用于别墅无防护结构的楼梯（防护栏焊接高1.3m） | F334: 1.一般用于别墅无防护结构的楼梯（防护栏焊接高1.3m） | G334: =#REF! -> #REF!
A335: 搭建临时楼梯 | B335: 跨 | C335: 3000 | D335: 按跨数计算，从一楼到二楼算一跨 两跨及以上，每增加一跨增加2500元 | E335: 1.适用范围：跃层、复式结构或别墅等无室内楼梯的户型； 2.搭建方式：木板或钢架楼梯框架+踏板。 | F335: 1.适用范围：跃层、复式结构或别墅等无室内楼梯的户型； 2.搭建方式：木板或钢架楼梯框架+踏板。 | G335: =#REF! -> #REF!
A336: 超高施工（局部超高） | B336: 项 | E336: 包含安全措施、高空作业人工补贴 | F336: ———————— | G336: =#REF! -> #REF!
A337: 超高施工（全屋超高） | B337: 项 | D337: 按超高区域地面面积计算 | E337: 包含安全措施、高空作业人工补贴 | F337: ———————— | G337: =#REF! -> #REF!
A338: 超高施工脚手架及安全措施费（层高5米以内） | B338: 项 | D338: 按项计算，包含移动脚手架 不含满堂红脚手架，满屋脚手架费用另计。 | E338: 包含超高区域搭建移动脚手架、超高施工安全措施，及脚手架拆除 | F338: 1.要求搭接牢固无安全隐患。 | G338: =#REF! -> #REF!
A339: 超高施工脚手架及安全措施费（层高8米以内） | B339: 项 | D339: 按项计算，包含移动脚手架 不含满堂红脚手架，满屋脚手架费用另计。 | E339: 包含超高区域搭建移动脚手架、超高施工安全措施，及脚手架拆除 | F339: 1.要求搭接牢固无安全隐患。 | G339: =#REF! -> #REF!
A340: 超高施工脚手架及安全措施费（层高8米以上） | B340: 项 | D340: 按项计算，包含移动脚手架 不含满堂红脚手架，满屋脚手架费用另计。 | E340: 包含超高区域搭建移动脚手架、超高施工安全措施，及脚手架拆除 | F340: 1.要求搭接牢固无安全隐患。 | G340: =#REF! -> #REF!
A341: 远程施工费（I类区域） | B341: 项 | C341: 0 | D341: 按项计算 以火车南站为坐标原点 I类区域： 一绕以内(四环)南至二绕以内(五环)区域,不计远程费 | E341: 远程范围：成都市绕城高速(一绕)以外区域，南门延至二绕以外区域 | F341: ———————— | G341: =#REF! -> #REF!
A342: 远程施工费（II类区域） | B342: 项 | C342: 7000 | D342: 按项计算 以火车南站为坐标原点 II类区域： 一绕以外(四环)南至二绕以外(五环)区域， 温江、青白江、龙泉、郫都、新都，7000元/户 | E342: 远程范围：成都市绕城高速(一绕)以外区域，南门延至二绕以外区域 | F342: ———————— | G342: =#REF! -> #REF!
A343: 远程施工费（III类区域） | B343: 项 | C343: 30000 | D343: 按项计算 以火车南站为坐标原点 III类区域： 二绕以外(五环)，金堂、彭州(三绕内)、崇州、大邑、邛崃、新津，30000元/户，接单面积150平米以上 | E343: 远程范围：成都市绕城高速(一绕)以外区域，南门延至二绕以外区域 | F343: ———————— | G343: =#REF! -> #REF!
A344: 远程施工费（IV类区域） | B344: 项 | C344: 50000 | D344: 按项计算 以火车南站为坐标原点 IV类区域： 眉山、都江堰、德阳，50000元/户，接单面积200平米以上 | E344: 远程范围：成都市绕城高速(一绕)以外区域，南门延至二绕以外区域 | F344: ———————— | G344: =#REF! -> #REF!
A345: 远程施工费（V类区域） | B345: 项 | C345: 80000 | D345: 按项计算 以火车南站为坐标原点 V类区域：超远项目 峨眉山、绵阳、自贡，80000元/户，接单面积300平米以上 以上范围外，费用另议。 | E345: 远程范围：成都市绕城高速(一绕)以外区域，南门延至二绕以外区域 | F345: ———————— | G345: =#REF! -> #REF!
A346: 精放线点工 | B346: 工日 | C346: 400 | D346: 按工日数计算 | E346: 只限于无法按计件工程量方式结算工资，如：现场管理、日常保洁、物料搬运、零星打拆、建渣清运、5S维护等 | F346: 只限于无法按计件工程量方式计算的零星工程，如：物料搬运、零星打拆、建渣清运、5S维护等 | G346: =#REF! -> #REF!
A347: 打拆点工 | B347: 工日 | C347: 300 | D347: 按工日数计算 | E347: 只限于无法按计件工程量方式结算工资，如：整改(含拆除)、成品安装、售后维修、软装施工、临时紧急情况突击等 | F347: 只限于无法按计件工程量方式计算的零星工程，如：零星砌筑、零星改造、零星安装等 | G347: =#REF! -> #REF!
A348: 砌墙/抹灰点工 | B348: 工日 | C348: 400 | D348: 按工日数计算 | E348: 只限于无法按计件工程量方式结算工资，如：整改(含拆除)、成品安装、售后维修、软装施工、临时紧急情况突击等 | F348: 只限于无法按计件工程量方式计算的零星工程，如：零星砌筑、零星改造、零星安装等 | G348: =#REF! -> #REF!
A349: 水电点工 | B349: 工日 | C349: 400 | D349: 按工日数计算 | E349: 只限于无法按计件工程量方式结算工资，如：整改(含拆除)、成品安装、售后维修、软装施工、临时紧急情况突击等 | F349: 只限于无法按计件工程量方式计算的零星工程，如：零星砌筑、零星改造、零星安装等 | G349: =#REF! -> #REF!
...
